Workbook

Sheet Finding right quantity
A2: Stock Name | B2: Code | C2: CMP | D2: Allocation | E2: Quantity | H2: Capital | I2: Actual
A3: ABDL | B3: NSE:ABDL | C3: =IFERROR(__xludf.DUMMYFUNCTION("GOOGLEFINANCE(B3)"),593.3) -> 593.3 | D3: =1/6 -> 0.16666667 | E3: =ROUND(($H$3*D3)/C3,0) -> #VALUE! | H3: 29,00,000 | I3: =SUMPRODUCT(E3:E9,C3:C9) -> #VALUE!
A4: UJIVAN | B4: NSE:NIFTYBEES | C4: =IFERROR(__xludf.DUMMYFUNCTION("GOOGLEFINANCE(B4)"),274.1) -> 274.1 | D4: =1/6 -> 0.16666667 | E4: =ROUND(($H$3*D4)/C4,0) -> #VALUE!
A5: AU | B5: NSE:SAMHI | C5: =IFERROR(__xludf.DUMMYFUNCTION("GOOGLEFINANCE(B5)"),158.58) -> 158.58 | D5: =1/6 -> 0.16666667 | E5: 408
A6: OSWAL PUMPS | B6: NSE:NH | C6: =IFERROR(__xludf.DUMMYFUNCTION("GOOGLEFINANCE(B6)"),1820.0) -> 1820 | D6: =1/6 -> 0.16666667 | E6: =ROUND(($H$3*D6)/C6,0) -> #VALUE!
A7: TD Power | B7: NSE:TDPOWERSYS | C7: =IFERROR(__xludf.DUMMYFUNCTION("GOOGLEFINANCE(B7)"),1227.9) -> 1227.9 | D7: =1/6 -> 0.16666667 | E7: =ROUND(($H$3*D7)/C7,0) -> #VALUE!
A8: Allied blenders | B8: NSE:ABDL | C8: =IFERROR(__xludf.DUMMYFUNCTION("GOOGLEFINANCE(B8)"),593.3) -> 593.3 | D8: 0.08 | E8: =ROUND(($H$3*D8)/C8,0) -> #VALUE!
A9: Tata Motors | B9: NSE:TATAMOTORS | C9: =IFERROR(__xludf.DUMMYFUNCTION("GOOGLEFINANCE(B9)"),"#N/A") -> #N/A | D9: =1/6 -> 0.16666667 | E9: 124
A13: New ideas
A14: Sansera | B14: must buy
A15: Jayaswal neco | B15: must buy

Sheet Tracker
A2: Stock Name | B2: Code | C2: Buy Price | D2: Quantity | E2: Investment | F2: CMP | G2: Change today | H2: Change today% | I2: Current value | J2: Gain/loss | K2: Gain/loss % | L2: Allocation (current) | M2: Allocation(Cost basis) | N2: Note
A3: =consolidated!A2 -> neuland | B3: =consolidated!B2 -> NSE:NEULANDLAB | C3: =consolidated!C2 -> 2699.5652 | D3: =consolidated!D2 -> 230 | E3: =C3*D3 -> 620900 | F3: =IFERROR(__xludf.DUMMYFUNCTION("GOOGLEFINANCE(B3)"),17750.0) -> 17750 | G3: =IFERROR(__xludf.DUMMYFUNCTION("GOOGLEFINANCE(B3,""change"")"),465.0) -> 465 | H3: =IFERROR(__xludf.DUMMYFUNCTION("GOOGLEFINANCE(B3,""changepct"")"),2.69) -> 2.69 | I3: =F3*D3 -> 4082500 | J3: =I3-E3 -> 3461600 | K3: =J3/E3 -> 5.5751329 | L3: =I3/$C$35 -> #REF! | M3: =E3/$C$33 -> #REF! | N3: Core
A4: =consolidated!A3 -> nh(6.1) | B4: =consolidated!B3 -> NSE:NH | C4: =consolidated!C3 -> 765.07969 | D4: =consolidated!D3 -> 1846 | E4: =C4*D4 -> 1412337.1 | F4: =IFERROR(__xludf.DUMMYFUNCTION("GOOGLEFINANCE(B4)"),1820.0) -> 1820 | G4: =IFERROR(__xludf.DUMMYFUNCTION("GOOGLEFINANCE(B4,""change"")"),-36.2) -> -36.2 | H4: =IFERROR(__xludf.DUMMYFUNCTION("GOOGLEFINANCE(B4,""changepct"")"),-1.95) -> -1.95 | I4: =F4*D4 -> 3359720 | J4: =I4-E4 -> 1947382.9 | K4: =J4/E4 -> 1.3788372 | L4: =I4/$C$35 -> #REF! | M4: =E4/$C$33 -> #REF! | N4: Core
A5: =consolidated!A4 -> SAMHI(5.8) | B5: =consolidated!B4 -> NSE:SAMHI | C5: =consolidated!C4 -> 186.07572 | D5: =consolidated!D4 -> 5341 | E5: =C5*D5 -> 993830.41 | F5: =IFERROR(__xludf.DUMMYFUNCTION("GOOGLEFINANCE(B5)"),158.58) -> 158.58 | G5: =IFERROR(__xludf.DUMMYFUNCTION("GOOGLEFINANCE(B5,""change"")"),0.22) -> 0.22 | H5: =IFERROR(__xludf.DUMMYFUNCTION("GOOGLEFINANCE(B5,""changepct"")"),0.14) -> 0.14 | I5: =F5*D5 -> 846975.78 | J5: =I5-E5 -> -146854.63 | K5: =J5/E5 -> -0.14776629 | L5: =I5/$C$35 -> #REF! | M5: =E5/$C$33 -> #REF! | N5: Core
A6: =#REF! -> #REF! | B6: =#REF! -> #REF! | C6: =#REF! -> #REF! | D6: =#REF! -> #REF! | E6: =C6*D6 -> #REF! | F6: =IFERROR(__xludf.DUMMYFUNCTION("GOOGLEFINANCE(B6)"),"#REF!") -> #REF! | G6: =IFERROR(__xludf.DUMMYFUNCTION("GOOGLEFINANCE(B6,""change"")"),"#REF!") -> #REF! | H6: =IFERROR(__xludf.DUMMYFUNCTION("GOOGLEFINANCE(B6,""changepct"")"),"#REF!") -> #REF! | I6: =F6*D6 -> #REF! | J6: =I6-E6 -> #REF! | K6: =J6/E6 -> #REF! | L6: =I6/$C$35 -> #REF! | M6: =E6/$C$33 -> #REF! | N6: core
A7: =consolidated!A5 -> JMFINANCIALS(4.3) | B7: =consolidated!B5 -> NSE:JMFINANCIL | C7: =consolidated!C5 -> 134.80569 | D7: =consolidated!D5 -> 15180 | E7: =C7*D7 -> 2046350.3 | F7: =IFERROR(__xludf.DUMMYFUNCTION("GOOGLEFINANCE(B7)"),145.37) -> 145.37 | G7: =IFERROR(__xludf.DUMMYFUNCTION("GOOGLEFINANCE(B7,""change"")"),2.52) -> 2.52 | H7: =IFERROR(__xludf.DUMMYFUNCTION("GOOGLEFINANCE(B7,""changepct"")"),1.76) -> 1.76 | I7: =F7*D7 -> 2206716.6 | J7: =I7-E7 -> 160366.3 | K7: =J7/E7 -> 0.078366983 | L7: =I7/$C$35 -> #REF! | M7: =E7/$C$33 -> #REF! | N7: Core
A8: =consolidated!A6 -> WINDLAS(2.4) | B8: =consolidated!B6 -> NSE:WINDLAS | C8: =consolidated!C6 -> 923.47437 | D8: =consolidated!D6 -> 1580 | E8: =C8*D8 -> 1459089.5 | F8: =IFERROR(__xludf.DUMMYFUNCTION("GOOGLEFINANCE(B8)"),826.0) -> 826 | G8: =IFERROR(__xludf.DUMMYFUNCTION("GOOGLEFINANCE(B8,""change"")"),-28.55) -> -28.55 | H8: =IFERROR(__xludf.DUMMYFUNCTION("GOOGLEFINANCE(B8,""changepct"")"),-3.34) -> -3.34 | I8: =F8*D8 -> 1305080 | J8: =I8-E8 -> -154009.5 | K8: =J8/E8 -> -0.10555178 | L8: =I8/$C$35 -> #REF! | M8: =E8/$C$35 -> #REF! | N8: core
A9: =consolidated!A7 -> SOLARA(sajal) | B9: =consolidated!B7 -> NSE:SOLARA | C9: =consolidated!C7 -> 635.97224 | D9: =consolidated!D7 -> 2422 | E9: =C9*D9 -> 1540324.8 | F9: =IFERROR(__xludf.DUMMYFUNCTION("GOOGLEFINANCE(B9)"),522.5) -> 522.5 | G9: =IFERROR(__xludf.DUMMYFUNCTION("GOOGLEFINANCE(B9,""change"")"),7.65) -> 7.65 | H9: =IFERROR(__xludf.DUMMYFUNCTION("GOOGLEFINANCE(B9,""changepct"")"),1.49) -> 1.49 | I9: =F9*D9 -> 1265495 | J9: =I9-E9 -> -274829.76 | K9: =J9/E9 -> -0.17842326 | L9: =I9/$C$35 -> #REF! | M9: =E9/$C$35 -> #REF! | N9: core
A10: =consolidated!A8 -> ABCAPITAL(5.9) | B10: =consolidated!B8 -> NSE:ABCAPITAL | C10: =consolidated!C8 -> 198.92308 | D10: =consolidated!D8 -> 6500 | E10: =C10*D10 -> 1293000 | F10: =IFERROR(__xludf.DUMMYFUNCTION("GOOGLEFINANCE(B10)"),362.3) -> 362.3 | G10: =IFERROR(__xludf.DUMMYFUNCTION("GOOGLEFINANCE(B10,""change"")"),-6.7) -> -6.7 | H10: =IFERROR(__xludf.DUMMYFUNCTION("GOOGLEFINANCE(B10,""changepct"")"),-1.82) -> -1.82 | I10: =F10*D10 -> 2354950 | J10: =I10-E10 -> 1061950 | K10: =J10/E10 -> 0.82130704 | L10: =I10/$C$35 -> #REF! | M10: =E10/$C$35 -> #REF! | N10: core
A11: =consolidated!A9 -> TDPOWERSYS(5.4) | B11: =consolidated!B9 -> NSE:TDPOWERSYS | C11: =consolidated!C9 -> 399.50652 | D11: =consolidated!D9 -> 4954 | E11: =C11*D11 -> 1979155.3 | F11: =IFERROR(__xludf.DUMMYFUNCTION("GOOGLEFINANCE(B11)"),1227.9) -> 1227.9 | G11: =IFERROR(__xludf.DUMMYFUNCTION("GOOGLEFINANCE(B11,""change"")"),-17.4) -> -17.4 | H11: =IFERROR(__xludf.DUMMYFUNCTION("GOOGLEFINANCE(B11,""changepct"")"),-1.4) -> -1.4 | I11: =F11*D11 -> 6083016.6 | J11: =I11-E11 -> 4103861.3 | K11: =J11/E11 -> 2.0735418 | L11: =I11/$C$35 -> #REF! | M11: =E11/$C$35 -> #REF! | N11: core
A12: =consolidated!A10 -> LAURUS(sajal) | B12: =consolidated!B10 -> NSE:LAURUSLABS | C12: =consolidated!C10 -> 571.02713 | D12: =consolidated!D10 -> 3280 | E12: =C12*D12 -> 1872969 | F12: =IFERROR(__xludf.DUMMYFUNCTION("GOOGLEFINANCE(B12)"),1225.2) -> 1225.2 | G12: =IFERROR(__xludf.DUMMYFUNCTION("GOOGLEFINANCE(B12,""change"")"),18.7) -> 18.7 | H12: =IFERROR(__xludf.DUMMYFUNCTION("GOOGLEFINANCE(B12,""changepct"")"),1.55) -> 1.55 | I12: =F12*D12 -> 4018656 | J12: =I12-E12 -> 2145687 | K12: =J12/E12 -> 1.1456073 | L12: =I12/$C$35 -> #REF! | M12: =E12/$C$35 -> #REF! | N12: core
A13: =#REF! -> #REF! | B13: =#REF! -> #REF! | C13: =#REF! -> #REF! | D13: =#REF! -> #REF! | E13: =C13*D13 -> #REF! | F13: =IFERROR(__xludf.DUMMYFUNCTION("GOOGLEFINANCE(B13)"),"#REF!") -> #REF! | G13: =IFERROR(__xludf.DUMMYFUNCTION("GOOGLEFINANCE(B13,""change"")"),"#REF!") -> #REF! | H13: =IFERROR(__xludf.DUMMYFUNCTION("GOOGLEFINANCE(B13,""changepct"")"),"#REF!") -> #REF! | I13: =F13*D13 -> #REF! | J13: =I13-E13 -> #REF! | K13: =J13/E13 -> #REF! | L13: =I13/$C$35 -> #REF! | M13: =E13/$C$35 -> #REF! | N13: satellite
A14: =#REF! -> #REF! | B14: =#REF! -> #REF! | C14: =#REF! -> #REF! | D14: =#REF! -> #REF! | E14: =C14*D14 -> #REF! | F14: =IFERROR(__xludf.DUMMYFUNCTION("GOOGLEFINANCE(B14)"),"#REF!") -> #REF! | G14: =IFERROR(__xludf.DUMMYFUNCTION("GOOGLEFINANCE(B14,""change"")"),"#REF!") -> #REF! | H14: =IFERROR(__xludf.DUMMYFUNCTION("GOOGLEFINANCE(B14,""changepct"")"),"#REF!") -> #REF! | I14: =F14*D14 -> #REF! | J14: =I14-E14 -> #REF! | K14: =J14/E14 -> #REF! | L14: =I14/$C$35 -> #REF! | M14: =E14/$C$35 -> #REF! | N14: core
A15: =#REF! -> #REF! | B15: =#REF! -> #REF! | C15: =#REF! -> #REF! | D15: =#REF! -> #REF! | E15: =C15*D15 -> #REF! | F15: =IFERROR(__xludf.DUMMYFUNCTION("GOOGLEFINANCE(B15)"),"#REF!") -> #REF! | G15: =IFERROR(__xludf.DUMMYFUNCTION("GOOGLEFINANCE(B15,""change"")"),"#REF!") -> #REF! | H15: =IFERROR(__xludf.DUMMYFUNCTION("GOOGLEFINANCE(B15,""changepct"")"),"#REF!") -> #REF! | I15: =F15*D15 -> #REF! | J15: =I15-E15 -> #REF! | K15: =J15/E15 -> #REF! | L15: =I15/$C$35 -> #REF! | M15: =E15/$C$35 -> #REF! | N15: core
A16: =#REF! -> #REF! | B16: =#REF! -> #REF! | C16: =#REF! -> #REF! | D16: =#REF! -> #REF! | E16: =C16*D16 -> #REF! | F16: =IFERROR(__xludf.DUMMYFUNCTION("GOOGLEFINANCE(B16)"),"#REF!") -> #REF! | G16: =IFERROR(__xludf.DUMMYFUNCTION("GOOGLEFINANCE(B16,""change"")"),"#REF!") -> #REF! | H16: =IFERROR(__xludf.DUMMYFUNCTION("GOOGLEFINANCE(B16,""changepct"")"),"#REF!") -> #REF! | I16: =F16*D16 -> #REF! | J16: =I16-E16 -> #REF! | K16: =J16/E16 -> #REF! | L16: =I16/$C$35 -> #REF! | M16: =E16/$C$35 -> #REF! | N16: core
A17: =consolidated!A11 -> ENTERO(4.6) | B17: =consolidated!B11 -> NSE:ENTERO | C17: =consolidated!C11 -> 1195.1178 | D17: =consolidated!D11 -> 1520 | E17: =C17*D17 -> 1816579 | F17: =IFERROR(__xludf.DUMMYFUNCTION("GOOGLEFINANCE(B17)"),1221.0) -> 1221 | G17: =IFERROR(__xludf.DUMMYFUNCTION("GOOGLEFINANCE(B17,""change"")"),-44.7) -> -44.7 | H17: =IFERROR(__xludf.DUMMYFUNCTION("GOOGLEFINANCE(B17,""changepct"")"),-3.53) -> -3.53 | I17: =F17*D17 -> 1855920 | J17: =I17-E17 -> 39340.984 | K17: =J17/E17 -> 0.021656632 | L17: =I17/$C$35 -> #REF! | M17: =E17/$C$35 -> #REF! | N17: core
A18: =#REF! -> #REF! | B18: =#REF! -> #REF! | C18: =#REF! -> #REF! | D18: =#REF! -> #REF! | E18: =C18*D18 -> #REF! | F18: =IFERROR(__xludf.DUMMYFUNCTION("GOOGLEFINANCE(B18)"),"#REF!") -> #REF! | G18: =IFERROR(__xludf.DUMMYFUNCTION("GOOGLEFINANCE(B18,""change"")"),"#REF!") -> #REF! | H18: =IFERROR(__xludf.DUMMYFUNCTION("GOOGLEFINANCE(B18,""changepct"")"),"#REF!") -> #REF! | I18: =F18*D18 -> #REF! | J18: =I18-E18 -> #REF! | K18: =J18/E18 -> #REF! | L18: =I18/$C$35 -> #REF! | M18: =E18/$C$35 -> #REF! | N18: core
A19: =#REF! -> #REF! | B19: =#REF! -> #REF! | C19: =#REF! -> #REF! | D19: =#REF! -> #REF! | E19: =C19*D19 -> #REF! | F19: =IFERROR(__xludf.DUMMYFUNCTION("GOOGLEFINANCE(B19)"),"#REF!") -> #REF! | G19: =IFERROR(__xludf.DUMMYFUNCTION("GOOGLEFINANCE(B19,""change"")"),"#REF!") -> #REF! | H19: =IFERROR(__xludf.DUMMYFUNCTION("GOOGLEFINANCE(B19,""changepct"")"),"#REF!") -> #REF! | I19: =F19*D19 -> #REF! | J19: =I19-E19 -> #REF! | K19: =J19/E19 -> #REF! | L19: =I19/$C$35 -> #REF! | M19: =E19/$C$35 -> #REF! | N19: core
A20: =#REF! -> #REF! | B20: =#REF! -> #REF! | C20: =#REF! -> #REF! | D20: =#REF! -> #REF! | E20: =C20*D20 -> #REF! | F20: =IFERROR(__xludf.DUMMYFUNCTION("GOOGLEFINANCE(B20)"),"#REF!") -> #REF! | G20: =IFERROR(__xludf.DUMMYFUNCTION("GOOGLEFINANCE(B20,""change"")"),"#REF!") -> #REF! | H20: =IFERROR(__xludf.DUMMYFUNCTION("GOOGLEFINANCE(B20,""changepct"")"),"#REF!") -> #REF! | I20: =F20*D20 -> #REF! | J20: =I20-E20 -> #REF! | K20: =J20/E20 -> #REF! | L20: =I20/$C$35 -> #REF! | M20: =E20/$C$35 -> #REF! | N20: core
A21: =consolidated!A12 -> INTERARCH(3.8) | B21: =consolidated!B12 -> NSE:INTERARCH | C21: =consolidated!C12 -> 1860.243 | D21: =consolidated!D12 -> 653 | E21: =C21*D21 -> 1214738.7 | F21: =IFERROR(__xludf.DUMMYFUNCTION("GOOGLEFINANCE(B21)"),2142.5) -> 2142.5 | G21: =IFERROR(__xludf.DUMMYFUNCTION("GOOGLEFINANCE(B21,""change"")"),-36.2) -> -36.2 | H21: =IFERROR(__xludf.DUMMYFUNCTION("GOOGLEFINANCE(B21,""changepct"")"),-1.66) -> -1.66 | I21: =F21*D21 -> 1399052.5 | J21: =I21-E21 -> 184313.83 | K21: =J21/E21 -> 0.15173126 | L21: =I21/$C$35 -> #REF! | M21: =E21/$C$35 -> #REF! | N21: core
A22: =consolidated!A13 -> PAYTM(4.5) | B22: =consolidated!B13 -> NSE:PAYTM | C22: =consolidated!C13 -> 970.38824 | D22: =consolidated!D13 -> 900 | E22: =C22*D22 -> 873349.42 | F22: =IFERROR(__xludf.DUMMYFUNCTION("GOOGLEFINANCE(B22)"),1188.0) -> 1188 | G22: =IFERROR(__xludf.DUMMYFUNCTION("GOOGLEFINANCE(B22,""change"")"),-9.4) -> -9.4 | H22: =IFERROR(__xludf.DUMMYFUNCTION("GOOGLEFINANCE(B22,""changepct"")"),-0.79) -> -0.79 | I22: =F22*D22 -> 1069200 | J22: =I22-E22 -> 195850.58 | K22: =J22/E22 -> 0.22425226 | L22: =I22/$C$35 -> #REF! | M22: =E22/$C$35 -> #REF! | N22: core
A23: =consolidated!A14 -> UJJIVANSFB(7) | B23: =consolidated!B14 -> NSE:UJJIVANSFB | C23: =consolidated!C14 -> 43.752222 | D23: =consolidated!D14 -> 36000 | E23: =C23*D23 -> 1575080 | F23: =IFERROR(__xludf.DUMMYFUNCTION("GOOGLEFINANCE(B23)"),62.4) -> 62.4 | G23: =IFERROR(__xludf.DUMMYFUNCTION("GOOGLEFINANCE(B23,""change"")"),-0.27) -> -0.27 | H23: =IFERROR(__xludf.DUMMYFUNCTION("GOOGLEFINANCE(B23,""changepct"")"),-0.43) -> -0.43 | I23: =F23*D23 -> 2246400 | J23: =I23-E23 -> 671320 | K23: =J23/E23 -> 0.42621327 | L23: =I23/$C$35 -> #REF! | M23: =E23/$C$35 -> #REF! | N23: core
A24: =consolidated!A15 -> FDC(Sajal) | B24: =consolidated!B15 -> NSE:FDC | C24: =consolidated!C15 -> 480.92838 | D24: =consolidated!D15 -> 3700 | E24: =C24*D24 -> 1779435 | F24: =IFERROR(__xludf.DUMMYFUNCTION("GOOGLEFINANCE(B24)"),380.25) -> 380.25 | G24: =IFERROR(__xludf.DUMMYFUNCTION("GOOGLEFINANCE(B24,""change"")"),4.7) -> 4.7 | H24: =IFERROR(__xludf.DUMMYFUNCTION("GOOGLEFINANCE(B24,""changepct"")"),1.25) -> 1.25 | I24: =F24*D24 -> 1406925 | J24: =I24-E24 -> -372510 | K24: =J24/E24 -> -0.20934173 | L24: =I24/$C$35 -> #REF! | M24: =E24/$C$35 -> #REF! | N24: core
A25: =#REF! -> #REF! | B25: =#REF! -> #REF! | C25: =#REF! -> #REF! | D25: =#REF! -> #REF! | E25: =C25*D25 -> #REF! | F25: =IFERROR(__xludf.DUMMYFUNCTION("GOOGLEFINANCE(B25)"),"#REF!") -> #REF! | G25: =IFERROR(__xludf.DUMMYFUNCTION("GOOGLEFINANCE(B25,""change"")"),"#REF!") -> #REF! | H25: =IFERROR(__xludf.DUMMYFUNCTION("GOOGLEFINANCE(B25,""changepct"")"),"#REF!") -> #REF! | I25: =F25*D25 -> #REF! | J25: =I25-E25 -> #REF! | K25: =J25/E25 -> #REF! | L25: =I25/$C$35 -> #REF! | M25: =E25/$C$35 -> #REF! | N25: core
A26: =#REF! -> #REF! | B26: =#REF! -> #REF! | C26: =#REF! -> #REF! | D26: =#REF! -> #REF! | E26: =C26*D26 -> #REF! | F26: =IFERROR(__xludf.DUMMYFUNCTION("GOOGLEFINANCE(B26)"),"#REF!") -> #REF! | G26: =IFERROR(__xludf.DUMMYFUNCTION("GOOGLEFINANCE(B26,""change"")"),"#REF!") -> #REF! | H26: =IFERROR(__xludf.DUMMYFUNCTION("GOOGLEFINANCE(B26,""changepct"")"),"#REF!") -> #REF! | I26: =F26*D26 -> #REF! | J26: =I26-E26 -> #REF! | K26: =J26/E26 -> #REF! | L26: =I26/$C$35 -> #REF! | M26: =E26/$C$35 -> #REF! | N26: core
A28: Cash | I28: =E28
H31: NEULAND | I31: SHIVALIK
B32: Starting date | C32: 45352 | D32: =(TODAY()-C32)/365 -> 2.1890411 | E32: Core Portfolio value | F32: =SUMIF(Table1[Note],"Core",Table1[Investment ]) -> #REF! | H32: =0.03*C35 -> #REF! | I32: =(1*C35)/100 -> #REF!
B33: Investment Value | C33: =SUM(E3:E28) -> #REF! | E33: Satellite Portfolio value | F33: =SUMIF(Table1[Note],"Sattelite",Table1[Investment ]) -> 0 | H33: =H32/F3 -> #REF! | I33: 1000
B34: Cash | C34: =E28
B35: Current value | C35: =SUM(I3:I27) -> #REF! | H35: STOCKS TO BUY
B36: Absolute returns | C36: =C35-C33 -> #REF! | H36: ABDL
B37: Absolute Return % | C37: =C36/C33 -> #REF! | H37: astra micro
B38: CAGR % | C38: =RATE(D32,0,-C33,C35,0) -> #REF! | H38: oswal
B39: XIRR | C39: =XIRR(XIRR!B2:B1001,XIRR!A2:A1001) -> #REF! | H39: ujjivan

Sheet XIRR
A1: Date | B1: Cashoflow | C1: Note
A2: 45352 | B2: -250000 | C2: Initial cashflow
A3: 45627 | B3: -50000 | C3: Addl cash
A4: 45717 | B4: -25000 | C4: Addl cash
A5: =TODAY() -> 46151 | B5: =Tracker!C35 -> #REF! | C5: Current value
A10: SAJALS 20 STOCKS
A11: LAURUS
A12: SANSERA
A13: SOLARA
A14: FDC
A15: DCAL
A16: EUREKA
A17: WINDLAS
A18: NEULAND (UNBDER WEIGHT)
A19: NH

Sheet Compare with the best
B4: Portfolio name | C4: Code | D4: NAV at the start date | E4: Current NAV | F4: Returns %
B5: My portfolio | C5: - | D5: - | E5: - | F5: =Tracker!C37 -> #REF!
B6: PPFAS | C6: MUTF_IN:PARA_PARI_FLEX_17J17OL | D6: 75.43 | E6: =IFERROR(__xludf.DUMMYFUNCTION("GOOGLEFINANCE(C6)"),91.94) -> 91.94 | F6: =E6/D6-1 -> 0.21887843
B7: Motilal mid cap fund | C7: MUTF_IN:MOTI_OSWA_MIDC_1E5B8T2 | D7: 87.63 | E7: =IFERROR(__xludf.DUMMYFUNCTION("GOOGLEFINANCE(C7)"),108.28) -> 108.28 | F7: =E7/D7-1 -> 0.23564989 | I7: =B5 -> My portfolio | J7: =F5 -> #REF!
I8: =B6 -> PPFAS | J8: =F6 -> 0.21887843
I9: =B7 -> Motilal mid cap fund | J9: =F7 -> 0.23564989

Sheet vibhanshu
A1: stock | B1: Stock tikr | C1: Average Buying price | D1: quantity | E1: CMP | F1: Investment | G1: Current value | H1: change today | I1: Over all change | J1: Allocation
A2: Neuland | B2: NSE:NEULANDLAB | C2: 1221.25 | D2: 80 | E2: =IFERROR(__xludf.DUMMYFUNCTION("GOOGLEFINANCE(B2,""PRICE"")"),17750.0) -> 17750 | F2: =C2*D2 -> 97700 | G2: =D2*E2 -> 1420000 | H2: =IFERROR(__xludf.DUMMYFUNCTION("GOOGLEFINANCE(B2,""changepct"")"),2.69) -> 2.69 | I2: =(E2-C2)/C2 -> 13.534289 | J2: =G2/G$27 -> 0.10355811
A3: nh | B3: NSE:NH | C3: 758.33333 | D3: 600 | E3: =IFERROR(__xludf.DUMMYFUNCTION("GOOGLEFINANCE(B3,""PRICE"")"),1820.0) -> 1820 | F3: =C3*D3 -> 455000 | G3: =D3*E3 -> 1092000 | H3: =IFERROR(__xludf.DUMMYFUNCTION("GOOGLEFINANCE(B3,""changepct"")"),-1.95) -> -1.95 | I3: =(E3-C3)/C3 -> 1.4 | J3: =G3/G$27 -> 0.079637649
A4: JMFINANCIALS | B4: NSE:JMFINANCIL | C4: 137.44028 | D4: 3930 | E4: =IFERROR(__xludf.DUMMYFUNCTION("GOOGLEFINANCE(B4,""PRICE"")"),145.37) -> 145.37 | F4: =C4*D4 -> 540140.3 | G4: =D4*E4 -> 571304.1 | H4: =IFERROR(__xludf.DUMMYFUNCTION("GOOGLEFINANCE(B4,""changepct"")"),1.76) -> 1.76 | I4: =(E4-C4)/C4 -> 0.057695751 | J4: =G4/G$27 -> 0.041664208
A5: SOLARA | B5: NSE:SOLARA | C5: 705.33 | D5: 772 | E5: =IFERROR(__xludf.DUMMYFUNCTION("GOOGLEFINANCE(B5,""PRICE"")"),522.5) -> 522.5 | F5: =C5*D5 -> 544514.76 | G5: =D5*E5 -> 403370 | H5: =IFERROR(__xludf.DUMMYFUNCTION("GOOGLEFINANCE(B5,""changepct"")"),1.49) -> 1.49 | I5: =(E5-C5)/C5 -> -0.259212 | J5: =G5/G$27 -> 0.029417068
A6: WINDLAS | B6: NSE:WINDLAS | C6: 969.55 | D6: 1130 | E6: =IFERROR(__xludf.DUMMYFUNCTION("GOOGLEFINANCE(B6,""PRICE"")"),826.0) -> 826 | F6: =C6*D6 -> 1095591.5 | G6: =D6*E6 -> 933380 | H6: =IFERROR(__xludf.DUMMYFUNCTION("GOOGLEFINANCE(B6,""changepct"")"),-3.34) -> -3.34 | I6: =(E6-C6)/C6 -> -0.14805838 | J6: =G6/G$27 -> 0.06806977
A7: ABCAPITAL | B7: NSE:ABCAPITAL | C7: 199.4 | D7: 2500 | E7: =IFERROR(__xludf.DUMMYFUNCTION("GOOGLEFINANCE(B7,""PRICE"")"),362.3) -> 362.3 | F7: =C7*D7 -> 498500 | G7: =D7*E7 -> 905750 | H7: =IFERROR(__xludf.DUMMYFUNCTION("GOOGLEFINANCE(B7,""changepct"")"),-1.82) -> -1.82 | I7: =(E7-C7)/C7 -> 0.81695085 | J7: =G7/G$27 -> 0.066054762
A8: TDPOWERSYS | B8: NSE:TDPOWERSYS | C8: 421.16555 | D8: 1053 | E8: =IFERROR(__xludf.DUMMYFUNCTION("GOOGLEFINANCE(B8,""PRICE"")"),1227.9) -> 1227.9 | F8: =C8*D8 -> 443487.32 | G8: =D8*E8 -> 1292978.7 | H8: =IFERROR(__xludf.DUMMYFUNCTION("GOOGLEFINANCE(B8,""changepct"")"),-1.4) -> -1.4 | I8: =(E8-C8)/C8 -> 1.9154806 | J8: =G8/G$27 -> 0.094294674
A9: LAURUS | B9: NSE:LAURUSLABS | C9: 589.86 | D9: 1610 | E9: =IFERROR(__xludf.DUMMYFUNCTION("GOOGLEFINANCE(B9,""PRICE"")"),1225.2) -> 1225.2 | F9: =C9*D9 -> 949674.6 | G9: =D9*E9 -> 1972572 | H9: =IFERROR(__xludf.DUMMYFUNCTION("GOOGLEFINANCE(B9,""changepct"")"),1.55) -> 1.55 | I9: =(E9-C9)/C9 -> 1.077103 | J9: =G9/G$27 -> 0.14385622
A10: ENTERO | B10: NSE:ENTERO | C10: 1164 | D10: 499 | E10: =IFERROR(__xludf.DUMMYFUNCTION("GOOGLEFINANCE(B10,""PRICE"")"),1221.0) -> 1221 | F10: =C10*D10 -> 580836 | G10: =D10*E10 -> 609279 | H10: =IFERROR(__xludf.DUMMYFUNCTION("GOOGLEFINANCE(B10,""changepct"")"),-3.53) -> -3.53 | I10: =(E10-C10)/C10 -> 0.048969072 | J10: =G10/G$27 -> 0.044433651
A11: NSE:INTERARCH | B11: NSE:INTERARCH | C11: 1823.8358 | D11: 203 | E11: =IFERROR(__xludf.DUMMYFUNCTION("GOOGLEFINANCE(B11,""PRICE"")"),2142.5) -> 2142.5 | F11: =C11*D11 -> 370238.67 | G11: =D11*E11 -> 434927.5 | H11: =IFERROR(__xludf.DUMMYFUNCTION("GOOGLEFINANCE(B11,""changepct"")"),-1.66) -> -1.66 | I11: =(E11-C11)/C11 -> 0.17472197 | J11: =G11/G$27 -> 0.031718501
A12: PAYTM | B12: NSE:PAYTM | C12: 957.74667 | D12: 300 | E12: =IFERROR(__xludf.DUMMYFUNCTION("GOOGLEFINANCE(B12,""PRICE"")"),1188.0) -> 1188 | F12: =C12*D12 -> 287324 | G12: =D12*E12 -> 356400 | H12: =IFERROR(__xludf.DUMMYFUNCTION("GOOGLEFINANCE(B12,""changepct"")"),-0.79) -> -0.79 | I12: =(E12-C12)/C12 -> 0.24041152 | J12: =G12/G$27 -> 0.025991628
A13: UJJIVANSFB | B13: NSE:UJJIVANSFB | C13: 43.81 | D13: 10000 | E13: =IFERROR(__xludf.DUMMYFUNCTION("GOOGLEFINANCE(B13,""PRICE"")"),62.4) -> 62.4 | F13: =C13*D13 -> 438100 | G13: =D13*E13 -> 624000 | H13: =IFERROR(__xludf.DUMMYFUNCTION("GOOGLEFINANCE(B13,""changepct"")"),-0.43) -> -0.43 | I13: =(E13-C13)/C13 -> 0.42433234 | J13: =G13/G$27 -> 0.045507228
A14: SILVERBEES | B14: NSE:SILVERBEES | C14: 128 | D14: 800 | E14: =IFERROR(__xludf.DUMMYFUNCTION("GOOGLEFINANCE(B14,""PRICE"")"),240.0) -> 240 | F14: =C14*D14 -> 102400 | G14: =D14*E14 -> 192000 | H14: =IFERROR(__xludf.DUMMYFUNCTION("GOOGLEFINANCE(B14,""changepct"")"),0.23) -> 0.23 | I14: =(E14-C14)/C14 -> 0.875 | J14: =G14/G$27 -> 0.014002224
A15: GOLD | B15: NSE:GOLDIETF | C15: 93.8 | D15: 1000 | E15: =IFERROR(__xludf.DUMMYFUNCTION("GOOGLEFINANCE(B15,""PRICE"")"),128.73) -> 128.73 | F15: =C15*D15 -> 93800 | G15: =D15*E15 -> 128730 | H15: =IFERROR(__xludf.DUMMYFUNCTION("GOOGLEFINANCE(B15,""changepct"")"),-0.16) -> -0.16 | I15: =(E15-C15)/C15 -> 0.37238806 | J15: =G15/G$27 -> 0.0093880536
A16: CSBBANK | B16: NSE:CSBBANK | C16: 382.79589 | D16: 1300 | E16: =IFERROR(__xludf.DUMMYFUNCTION("GOOGLEFINANCE(B16,""PRICE"")"),365.0) -> 365 | F16: =C16*D16 -> 497634.66 | G16: =D16*E16 -> 474500 | H16: =IFERROR(__xludf.DUMMYFUNCTION("GOOGLEFINANCE(B16,""changepct"")"),2.26) -> 2.26 | I16: =(E16-C16)/C16 -> -0.046489246 | J16: =G16/G$27 -> 0.034604454
A17: POCL | B17: NSE:POCL | C17: 1348.18 | D17: 197 | E17: =IFERROR(__xludf.DUMMYFUNCTION("GOOGLEFINANCE(B17,""PRICE"")"),1430.5) -> 1430.5 | F17: =C17*D17 -> 265591.46 | G17: =D17*E17 -> 281808.5 | H17: =IFERROR(__xludf.DUMMYFUNCTION("GOOGLEFINANCE(B17,""changepct"")"),-0.4) -> -0.4 | I17: =(E17-C17)/C17 -> 0.061060096 | J17: =G17/G$27 -> 0.020551801
A18: MCX | B18: NSE:MCX | C18: =9516.36/5 -> 1903.272 | D18: =55*5 -> 275 | E18: =IFERROR(__xludf.DUMMYFUNCTION("GOOGLEFINANCE(B18,""PRICE"")"),3098.0) -> 3098 | F18: =C18*D18 -> 523399.8 | G18: =D18*E18 -> 851950 | H18: =IFERROR(__xludf.DUMMYFUNCTION("GOOGLEFINANCE(B18,""changepct"")"),1.82) -> 1.82 | I18: =(E18-C18)/C18 -> 0.62772321 | J18: =G18/G$27 -> 0.062131222
A19: ACUTAS | B19: NSE:ACUTAAS | C19: 1727.5 | D19: 200 | E19: =IFERROR(__xludf.DUMMYFUNCTION("GOOGLEFINANCE(B19,""PRICE"")"),2745.1) -> 2745.1 | F19: =C19*D19 -> 345500 | G19: =D19*E19 -> 549020 | H19: =IFERROR(__xludf.DUMMYFUNCTION("GOOGLEFINANCE(B19,""changepct"")"),0.71) -> 0.71 | I19: =(E19-C19)/C19 -> 0.58905933 | J19: =G19/G$27 -> 0.040039068
A20: AARTPHARM | B20: NSE:AARTIPHARM | C20: 753.69 | D20: 150 | E20: =IFERROR(__xludf.DUMMYFUNCTION("GOOGLEFINANCE(B20,""PRICE"")"),767.0) -> 767 | F20: =C20*D20 -> 113053.5 | G20: =D20*E20 -> 115050 | H20: =IFERROR(__xludf.DUMMYFUNCTION("GOOGLEFINANCE(B20,""changepct"")"),-1.37) -> -1.37 | I20: =(E20-C20)/C20 -> 0.017659781 | J20: =G20/G$27 -> 0.0083903951
A21: SANSERA | B21: NSE:SANSERA | C21: 1820 | D21: 50 | E21: =IFERROR(__xludf.DUMMYFUNCTION("GOOGLEFINANCE(B21,""PRICE"")"),2521.8) -> 2521.8 | F21: =C21*D21 -> 91000 | G21: =D21*E21 -> 126090 | H21: =IFERROR(__xludf.DUMMYFUNCTION("GOOGLEFINANCE(B21,""changepct"")"),-1.03) -> -1.03 | I21: =(E21-C21)/C21 -> 0.3856044 | J21: =G21/G$27 -> 0.009195523
A22: SNACOMS | B22: NSE:SONACOMS | C22: 524.17 | D22: 600 | E22: =IFERROR(__xludf.DUMMYFUNCTION("GOOGLEFINANCE(B22,""PRICE"")"),579.65) -> 579.65 | F22: =C22*D22 -> 314502 | G22: =D22*E22 -> 347790 | H22: =IFERROR(__xludf.DUMMYFUNCTION("GOOGLEFINANCE(B22,""changepct"")"),0.17) -> 0.17 | I22: =(E22-C22)/C22 -> 0.10584352 | J22: =G22/G$27 -> 0.025363716
A23: J&KBANK | B23: NSE:J&KBANK | C23: 116.19 | D23: 207 | E23: =IFERROR(__xludf.DUMMYFUNCTION("GOOGLEFINANCE(B23,""PRICE"")"),141.1) -> 141.1 | F23: =C23*D23 -> 24051.33 | G23: =D23*E23 -> 29207.7 | H23: =IFERROR(__xludf.DUMMYFUNCTION("GOOGLEFINANCE(B23,""changepct"")"),1.05) -> 1.05 | I23: =(E23-C23)/C23 -> 0.21439022 | J23: =G23/G$27 -> 0.0021300664
F27: =SUM(F2:F23) -> 8672039.9 | G27: =SUM(G2:G23) -> 13712108

Sheet US portfolio
A1: stock | B1: Stock tikr | C1: Average Buying price | D1: quantity | E1: CMP | F1: Investment | G1: Current value | H1: change today | I1: Over all change | J1: Allocation
A2: SIL | B2: SIL | C2: 85.09 | D2: 23.43646 | E2: =IFERROR(__xludf.DUMMYFUNCTION("GOOGLEFINANCE(B2,""PRICE"")"),97.24) -> 97.24 | F2: =C2*D2 -> 1994.2084 | G2: =D2*E2 -> 2278.9614 | H2: =IFERROR(__xludf.DUMMYFUNCTION("GOOGLEFINANCE(B2,""changepct"")"),3.17) -> 3.17 | I2: =(E2-C2)/C2 -> 0.14278999 | J2: =G2/G$15 -> 0.082401181 | L2: MANJARI | M2: CASH
A3: REMX | B3: REMX | C3: 87.06 | D3: 14.888834 | E3: =IFERROR(__xludf.DUMMYFUNCTION("GOOGLEFINANCE(B3,""PRICE"")"),106.38) -> 106.38 | F3: =C3*D3 -> 1296.2219 | G3: =D3*E3 -> 1583.8742 | M3: 1360
A4: GDX | B4: GDX | C4: 84.2 | D4: 11.841568 | E4: =IFERROR(__xludf.DUMMYFUNCTION("GOOGLEFINANCE(B4,""PRICE"")"),94.59) -> 94.59 | F4: =C4*D4 -> 997.06003 | G4: =D4*E4 -> 1120.0939 | H4: =IFERROR(__xludf.DUMMYFUNCTION("GOOGLEFINANCE(B4,""changepct"")"),3.13) -> 3.13 | I4: =(E4-C4)/C4 -> 0.12339667 | J4: =G4/G$15 -> 0.040499617
A5: BE | B5: BE | C5: 278 | D5: 6.097122 | E5: =IFERROR(__xludf.DUMMYFUNCTION("GOOGLEFINANCE(B5,""PRICE"")"),261.03) -> 261.03 | F5: =C5*D5 -> 1694.9999 | G5: =D5*E5 -> 1591.5318 | H5: =IFERROR(__xludf.DUMMYFUNCTION("GOOGLEFINANCE(B5,""changepct"")"),0.92) -> 0.92 | I5: =(E5-C5)/C5 -> -0.061043165 | J5: =G5/G$15 -> 0.057545555
A6: GLD | B6: GLD | C6: 425.15 | D6: 14.794255 | E6: =IFERROR(__xludf.DUMMYFUNCTION("GOOGLEFINANCE(B6,""PRICE"")"),433.77) -> 433.77 | F6: =C6*D6 -> 6289.7775 | G6: =D6*E6 -> 6417.304 | H6: =IFERROR(__xludf.DUMMYFUNCTION("GOOGLEFINANCE(B6,""changepct"")"),0.48) -> 0.48 | I6: =(E6-C6)/C6 -> 0.020275197 | J6: =G6/G$15 -> 0.23203264
A7: URNM | B7: URNM | C7: 64.78 | D7: 15.392667 | E7: =IFERROR(__xludf.DUMMYFUNCTION("GOOGLEFINANCE(B7,""PRICE"")"),64.99) -> 64.99 | F7: =C7*D7 -> 997.13697 | G7: =D7*E7 -> 1000.3694 | H7: =IFERROR(__xludf.DUMMYFUNCTION("GOOGLEFINANCE(B7,""changepct"")"),-3.01) -> -3.01 | I7: =(E7-C7)/C7 -> 0.0032417413 | J7: =G7/G$15 -> 0.036170698
A8: SLV | B8: SLV | C8: 65.68 | D8: 30.361738 | E8: =IFERROR(__xludf.DUMMYFUNCTION("GOOGLEFINANCE(B8,""PRICE"")"),73.01) -> 73.01 | F8: =C8*D8 -> 1994.159 | G8: =D8*E8 -> 2216.7105 | H8: =IFERROR(__xludf.DUMMYFUNCTION("GOOGLEFINANCE(B8,""changepct"")"),1.97) -> 1.97 | I8: =(E8-C8)/C8 -> 0.11160171 | J8: =G8/G$15 -> 0.080150355
A9: Rocket labs | B9: RKLB | C9: 45 | D9: 10 | E9: =IFERROR(__xludf.DUMMYFUNCTION("GOOGLEFINANCE(B9,""PRICE"")"),105.47) -> 105.47 | F9: =C9*D9 -> 450 | G9: =D9*E9 -> 1054.7 | H9: =IFERROR(__xludf.DUMMYFUNCTION("GOOGLEFINANCE(B9,""changepct"")"),34.22) -> 34.22 | I9: =(E9-C9)/C9 -> 1.3437778 | J9: =G9/G$15 -> 0.038135147
A10: COPX | B10: COPX | C10: 77 | D10: 22.013006 | E10: =IFERROR(__xludf.DUMMYFUNCTION("GOOGLEFINANCE(B10,""PRICE"")"),85.97) -> 85.97 | F10: =C10*D10 -> 1695.0015 | G10: =D10*E10 -> 1892.4581 | H10: =IFERROR(__xludf.DUMMYFUNCTION("GOOGLEFINANCE(B10,""changepct"")"),4.07) -> 4.07 | I10: =(E10-C10)/C10 -> 0.11649351 | J10: =G10/G$15 -> 0.068426252
A11: GRID | B11: GRID | C11: 168.76 | D11: 10.043631 | E11: =IFERROR(__xludf.DUMMYFUNCTION("GOOGLEFINANCE(B11,""PRICE"")"),197.22) -> 197.22 | F11: =C11*D11 -> 1694.9632 | G11: =D11*E11 -> 1980.8049 | H11: =IFERROR(__xludf.DUMMYFUNCTION("GOOGLEFINANCE(B11,""changepct"")"),2.26) -> 2.26 | I11: =(E11-C11)/C11 -> 0.16864186 | J11: =G11/G$15 -> 0.071620636
A12: PAVE | B12: PAVE | C12: 54.14 | D12: 36.829991 | E12: =IFERROR(__xludf.DUMMYFUNCTION("GOOGLEFINANCE(B12,""PRICE"")"),53.17) -> 53.17 | F12: =C12*D12 -> 1993.9757 | G12: =D12*E12 -> 1958.2506 | H12: =IFERROR(__xludf.DUMMYFUNCTION("GOOGLEFINANCE(B12,""changepct"")"),-1.15) -> -1.15 | I12: =(E12-C12)/C12 -> -0.017916513 | J12: =G12/G$15 -> 0.070805134
A13: SII | B13: SII | C13: 138.49 | D13: 32.397152 | E13: =IFERROR(__xludf.DUMMYFUNCTION("GOOGLEFINANCE(B13,""PRICE"")"),140.81) -> 140.81 | F13: =C13*D13 -> 4486.6816 | G13: =D13*E13 -> 4561.843 | H13: =IFERROR(__xludf.DUMMYFUNCTION("GOOGLEFINANCE(B13,""changepct"")"),-1.09) -> -1.09 | I13: =(E13-C13)/C13 -> 0.016752112 | J13: =G13/G$15 -> 0.16494411 | L13: VIBHANSHU
F15: =SUM(F2:F13) -> 25584.186 | G15: =SUM(G2:G13) -> 27656.902 | I15: =G15-F15 -> 2072.7162
A17: stock | B17: Stock tikr | C17: Average Buying price | D17: quantity | E17: CMP | F17: Investment | G17: Current value | H17: change today | I17: Over all change | J17: Allocation
A18: SIL | B18: SIL | C18: 90.2 | D18: 44.217749 | E18: =IFERROR(__xludf.DUMMYFUNCTION("GOOGLEFINANCE(B18,""PRICE"")"),97.24) -> 97.24 | F18: =C18*D18 -> 3988.441 | G18: =D18*E18 -> 4299.734 | H18: =IFERROR(__xludf.DUMMYFUNCTION("GOOGLEFINANCE(B18,""changepct"")"),3.17) -> 3.17 | I18: =(E18-C18)/C18 -> 0.07804878 | J18: =G18/G$31 -> 0.11980475 | M18: CASH
A19: SII | B19: SII | C19: 135.46 | D19: 22.081365 | E19: =IFERROR(__xludf.DUMMYFUNCTION("GOOGLEFINANCE(B19,""PRICE"")"),140.81) -> 140.81 | F19: =C19*D19 -> 2991.1416 | G19: =D19*E19 -> 3109.2769 | H19: =IFERROR(__xludf.DUMMYFUNCTION("GOOGLEFINANCE(B19,""changepct"")"),-1.09) -> -1.09 | I19: =(E19-C19)/C19 -> 0.039495054 | J19: =G19/G$31 -> 0.086634699 | M19: 2035
A20: GDX | B20: GDX | C20: 90.76 | D20: 39.549971 | E20: =IFERROR(__xludf.DUMMYFUNCTION("GOOGLEFINANCE(B20,""PRICE"")"),94.59) -> 94.59 | F20: =C20*D20 -> 3589.5553 | G20: =D20*E20 -> 3741.0317 | H20: =IFERROR(__xludf.DUMMYFUNCTION("GOOGLEFINANCE(B20,""changepct"")"),3.13) -> 3.13 | I20: =(E20-C20)/C20 -> 0.042199207 | J20: =G20/G$31 -> 0.10423747
A21: SILJ | B21: SILJ
A22: BE | B22: BE | C22: 236.08 | D22: 8.4469554 | E22: =IFERROR(__xludf.DUMMYFUNCTION("GOOGLEFINANCE(B22,""PRICE"")"),261.03) -> 261.03 | F22: =C22*D22 -> 1994.1572 | G22: =D22*E22 -> 2204.9088 | H22: =IFERROR(__xludf.DUMMYFUNCTION("GOOGLEFINANCE(B22,""changepct"")"),0.92) -> 0.92 | I22: =(E22-C22)/C22 -> 0.10568451 | J22: =G22/G$31 -> 0.061436022
A23: COPX | B23: COPX | C23: 82.1 | D23: 48.576035 | E23: =IFERROR(__xludf.DUMMYFUNCTION("GOOGLEFINANCE(B23,""PRICE"")"),85.97) -> 85.97 | F23: =C23*D23 -> 3988.0925 | G23: =D23*E23 -> 4176.0818 | H23: =IFERROR(__xludf.DUMMYFUNCTION("GOOGLEFINANCE(B23,""changepct"")"),4.07) -> 4.07 | I23: =(E23-C23)/C23 -> 0.047137637 | J23: =G23/G$31 -> 0.1163594 | L23: =F31+F15 -> 60179.027
A24: URNM | B24: URNM | C24: 67.51 | D24: 44.310226 | E24: =IFERROR(__xludf.DUMMYFUNCTION("GOOGLEFINANCE(B24,""PRICE"")"),64.99) -> 64.99 | F24: =C24*D24 -> 2991.3834 | G24: =D24*E24 -> 2879.7216 | H24: =IFERROR(__xludf.DUMMYFUNCTION("GOOGLEFINANCE(B24,""changepct"")"),-3.01) -> -3.01 | I24: =(E24-C24)/C24 -> -0.037327803 | J24: =G24/G$31 -> 0.080238531
A25: WDGF | B25: WDGF | C25: 34.94 | D25: 29 | E25: =IFERROR(__xludf.DUMMYFUNCTION("GOOGLEFINANCE(B25,""PRICE"")"),32.29) -> 32.29 | F25: =C25*D25 -> 1013.26 | G25: =D25*E25 -> 936.41 | H25: =IFERROR(__xludf.DUMMYFUNCTION("GOOGLEFINANCE(B25,""changepct"")"),0.4) -> 0.4 | I25: =(E25-C25)/C25 -> -0.075844305 | J25: =G25/G$31 -> 0.026091467
A26: GRID | B26: GRID | C26: 178.68 | D26: 19.530595 | E26: =IFERROR(__xludf.DUMMYFUNCTION("GOOGLEFINANCE(B26,""PRICE"")"),197.22) -> 197.22 | F26: =C26*D26 -> 3489.7267 | G26: =D26*E26 -> 3851.8239 | H26: =IFERROR(__xludf.DUMMYFUNCTION("GOOGLEFINANCE(B26,""changepct"")"),2.26) -> 2.26 | I26: =(E26-C26)/C26 -> 0.10376091 | J26: =G26/G$31 -> 0.1073245
A27: GLD | B27: GLD | C27: 435.89 | D27: 10.293468 | E27: =IFERROR(__xludf.DUMMYFUNCTION("GOOGLEFINANCE(B27,""PRICE"")"),433.77) -> 433.77 | F27: =C27*D27 -> 4486.82 | G27: =D27*E27 -> 4464.9978 | H27: =IFERROR(__xludf.DUMMYFUNCTION("GOOGLEFINANCE(B27,""changepct"")"),0.48) -> 0.48 | I27: =(E27-C27)/C27 -> -0.0048636124 | J27: =G27/G$31 -> 0.12440955
A28: SLV | B28: SLV | C28: 68.86 | D28: 51.839275 | E28: =IFERROR(__xludf.DUMMYFUNCTION("GOOGLEFINANCE(B28,""PRICE"")"),73.01) -> 73.01 | F28: =C28*D28 -> 3569.6524 | G28: =D28*E28 -> 3784.7854 | H28: =IFERROR(__xludf.DUMMYFUNCTION("GOOGLEFINANCE(B28,""changepct"")"),1.97) -> 1.97 | I28: =(E28-C28)/C28 -> 0.060267209 | J28: =G28/G$31 -> 0.10545659
A30: PAVE | B30: PAVE | C30: 54.3 | D30: 45.904434 | E30: =IFERROR(__xludf.DUMMYFUNCTION("GOOGLEFINANCE(B30,""PRICE"")"),53.17) -> 53.17 | F30: =C30*D30 -> 2492.6108 | G30: =D30*E30 -> 2440.7388 | H30: =IFERROR(__xludf.DUMMYFUNCTION("GOOGLEFINANCE(B30,""changepct"")"),-1.15) -> -1.15 | I30: =(E30-C30)/C30 -> -0.020810313 | J30: =G30/G$31 -> 0.068007022
F31: =SUM(F18:F30) -> 34594.841 | G31: =SUM(G18:G30) -> 35889.511 | I31: =G31-F31 -> 1294.6697
A32: stock | B32: Stock tikr | C32: Average Buying price | D32: quantity | E32: CMP | F32: Investment | G32: Current value | H32: change today | I32: Over all change | J32: Allocation
L34: GOLD MINERS | M34: =J35+J34 -> 0
L35: SILVER MINERS | M35: =J36+J33+J37 -> 0
L36: US EQUITY | M36: =J41+J40 -> 0.0368851
L37: GOLD | M37: =J38 -> 0.38057721
A38: GLD | B38: GLD | C38: =((C27*D27)+(C6*D6))/D38 -> 429.55661 | D38: =D27+D6 -> 25.087723 | E38: =IFERROR(__xludf.DUMMYFUNCTION("GOOGLEFINANCE(B38,""PRICE"")"),433.77) -> 433.77 | F38: =C38*D38 -> 10776.597 | G38: =D38*E38 -> 10882.302 | H38: =IFERROR(__xludf.DUMMYFUNCTION("GOOGLEFINANCE(B38,""changepct"")"),0.48) -> 0.48 | I38: =(E38-C38)/C38 -> 0.0098086919 | J38: =G38/G$50 -> 0.38057721 | L38: COPPER | M38: =J42
L39: URANIUM | M39: =J39
L40: DEFENCE | M40: =J43 -> 0.032748247
A41: Rocket labs | B41: RKLB | C41: 45 | D41: 10 | E41: =IFERROR(__xludf.DUMMYFUNCTION("GOOGLEFINANCE(B41,""PRICE"")"),105.47) -> 105.47 | F41: =C41*D41 -> 450 | G41: =D41*E41 -> 1054.7 | H41: =IFERROR(__xludf.DUMMYFUNCTION("GOOGLEFINANCE(B41,""changepct"")"),34.22) -> 34.22 | I41: =(E41-C41)/C41 -> 1.3437778 | J41: =G41/G$50 -> 0.0368851 | L41: ELECTRIFICATION | M41: =J44+J46 -> 0.35782143
L42: SILVER | M42: =J45 -> 0.032430675
A43: WDGF | B43: WDGF | C43: =C25 -> 34.94 | D43: =D25 -> 29 | E43: =IFERROR(__xludf.DUMMYFUNCTION("GOOGLEFINANCE(B43,""PRICE"")"),32.29) -> 32.29 | F43: =C43*D43 -> 1013.26 | G43: =D43*E43 -> 936.41 | H43: =IFERROR(__xludf.DUMMYFUNCTION("GOOGLEFINANCE(B43,""changepct"")"),0.4) -> 0.4 | I43: =(E43-C43)/C43 -> -0.075844305 | J43: =G43/G$50 -> 0.032748247
A44: GRID | B44: GRID | C44: =((C26*D26)+(C11*D11))/D44 -> 175.31109 | D44: =D26+D11 -> 29.574226 | E44: =IFERROR(__xludf.DUMMYFUNCTION("GOOGLEFINANCE(B44,""PRICE"")"),197.22) -> 197.22 | F44: =C44*D44 -> 5184.6899 | G44: =D44*E44 -> 5832.6288 | H44: =IFERROR(__xludf.DUMMYFUNCTION("GOOGLEFINANCE(B44,""changepct"")"),2.26) -> 2.26 | I44: =(E44-C44)/C44 -> 0.1249716 | J44: =G44/G$50 -> 0.20397942 | K44: =IFERROR(__xludf.DUMMYFUNCTION("GOOGLEFINANCE(""CURRENCY:USDINR"")"),94.42550000000001) -> 94.4255
A45: SLV | B45: SLV | C45: 78.5 | D45: 12.701401 | E45: =IFERROR(__xludf.DUMMYFUNCTION("GOOGLEFINANCE(B45,""PRICE"")"),73.01) -> 73.01 | F45: =C45*D45 -> 997.05998 | G45: =D45*E45 -> 927.32929 | H45: =IFERROR(__xludf.DUMMYFUNCTION("GOOGLEFINANCE(B45,""changepct"")"),1.97) -> 1.97 | I45: =(E45-C45)/C45 -> -0.069936306 | J45: =G45/G$50 -> 0.032430675 | L45: =K44*(M3+M19) -> 320574.57
A46: PAVE | B46: PAVE | C46: =((C30*D30)+(C12*D12))/D46 -> 54.228775 | D46: =D12+D30 -> 82.734425 | E46: =IFERROR(__xludf.DUMMYFUNCTION("GOOGLEFINANCE(B46,""PRICE"")"),53.17) -> 53.17 | F46: =C46*D46 -> 4486.5865 | G46: =D46*E46 -> 4398.9894 | H46: =IFERROR(__xludf.DUMMYFUNCTION("GOOGLEFINANCE(B46,""changepct"")"),-1.15) -> -1.15 | I46: =(E46-C46)/C46 -> -0.01952422 | J46: =G46/G$50 -> 0.153842
A47: SII | B47: SII | C47: =C13 -> 138.49 | D47: =D13 -> 32.397152 | E47: =IFERROR(__xludf.DUMMYFUNCTION("GOOGLEFINANCE(B47,""PRICE"")"),140.81) -> 140.81 | F47: =C47*D47 -> 4486.6816 | G47: =D47*E47 -> 4561.843 | H47: =IFERROR(__xludf.DUMMYFUNCTION("GOOGLEFINANCE(B47,""changepct"")"),-1.09) -> -1.09 | I47: =(E47-C47)/C47 -> 0.016752112 | J47: =G47/G$50 -> 0.15953734
A48: WDEF | B48: WDEF | C48: =C29 | D48: =D29 | E48: =IFERROR(__xludf.DUMMYFUNCTION("GOOGLEFINANCE(B48,""PRICE"")"),29.45) -> 29.45 | F48: =C48*D48 -> 0 | G48: =D48*E48 -> 0 | H48: =IFERROR(__xludf.DUMMYFUNCTION("GOOGLEFINANCE(B48,""changepct"")"),-2.17) -> -2.17 | I48: =(E48-C48)/C48 -> #DIV/0! | J48: =G48/G$50 -> 0
F50: =SUM(F33:F48) -> 27394.875 | G50: =SUM(G33:G48) -> 28594.202 | I50: =G50-F50 -> 1199.3269 | J50: =I50/F50 -> 0.043779243
E51: Total US pORTFOLIO IN INR | F51: =F50*K44 -> 2586774.8 | G51: =G50*K44 -> 2700021.8
K52: =I50*K44 -> 113247.04
E53: GOLD and Silver | G53: =(M34+M35+M37)*G51 -> 1027566.8 | H53: GOLD | I53: =M37*G51 -> 1027566.8 | K53: =F50*K44 -> 2586774.8
H54: GOLD MINER | I54: =M34*G51 -> 0
H55: SILVER MINER | I55: =M35*G51 -> 0
H56: SILVER | I56: =M42*G51 -> 87563.532
E58: CASH | F58: =26945*K44 -> 2544295.1 | G58: VIB
F59: =21270*K44 -> 2008430.4 | G59: MANJ
A63: Copper notes
A64: Current producing copper businesses are much less tahn what they are

Sheet HUF
A1: Column 1 | B1: Average Buying price | C1: quantity | D1: CMP | E1: Investment | F1: Current value | G1: change today | H1: Over all change | I1: Allocation | J1: Column 1 2
A2: NSE:NH | B2: 808.27 | C2: 650 | D2: =IFERROR(__xludf.DUMMYFUNCTION("GOOGLEFINANCE(A2,""PRICE"")"),1820.0) -> 1820 | E2: =B2*C2 -> 525375.5 | F2: =C2*D2 -> 1183000 | G2: =IFERROR(__xludf.DUMMYFUNCTION("GOOGLEFINANCE(A2,""changepct"")"),-1.95) -> -1.95 | H2: =(D2-B2)/B2 -> 1.2517228 | I2: =F2/F$28 -> 0.066971993 | J2: =F2-E2 -> 657624.5
A3: NSE:NEULANDLAB | B3: 5900 | C3: 70 | D3: =IFERROR(__xludf.DUMMYFUNCTION("GOOGLEFINANCE(A3,""PRICE"")"),17750.0) -> 17750 | E3: =B3*C3 -> 413000 | F3: =C3*D3 -> 1242500 | G3: =IFERROR(__xludf.DUMMYFUNCTION("GOOGLEFINANCE(A3,""changepct"")"),2.69) -> 2.69 | H3: =(D3-B3)/B3 -> 2.0084746 | I3: =F3/F$28 -> 0.070340407 | J3: =F3-E3 -> 829500
A4: NSE:SAMHI | B4: 186.64761 | C4: 2725 | D4: =IFERROR(__xludf.DUMMYFUNCTION("GOOGLEFINANCE(A4,""PRICE"")"),158.58) -> 158.58 | E4: =B4*C4 -> 508614.73 | F4: =C4*D4 -> 432130.5 | G4: =IFERROR(__xludf.DUMMYFUNCTION("GOOGLEFINANCE(A4,""changepct"")"),0.14) -> 0.14 | H4: =(D4-B4)/B4 -> -0.15037754 | I4: =F4/F$28 -> 0.024463771 | J4: =F4-E4 -> -76484.231
A5: NSE:JMFINANCIL | B5: 132.17265 | C5: 5850 | D5: =IFERROR(__xludf.DUMMYFUNCTION("GOOGLEFINANCE(A5,""PRICE"")"),145.37) -> 145.37 | E5: =B5*C5 -> 773210 | F5: =C5*D5 -> 850414.5 | G5: =IFERROR(__xludf.DUMMYFUNCTION("GOOGLEFINANCE(A5,""changepct"")"),1.76) -> 1.76 | H5: =(D5-B5)/B5 -> 0.099849329 | I5: =F5/F$28 -> 0.048143663 | J5: =F5-E5 -> 77204.5
A6: NSE:SOLARA | B6: 598.24706 | C6: 850 | D6: =IFERROR(__xludf.DUMMYFUNCTION("GOOGLEFINANCE(A6,""PRICE"")"),522.5) -> 522.5 | E6: =B6*C6 -> 508510 | F6: =C6*D6 -> 444125 | G6: =IFERROR(__xludf.DUMMYFUNCTION("GOOGLEFINANCE(A6,""changepct"")"),1.49) -> 1.49 | H6: =(D6-B6)/B6 -> -0.12661501 | I6: =F6/F$28 -> 0.025142803 | J6: =F6-E6 -> -64385
A7: NSE:TDPOWERSYS | B7: 353.41895 | C7: 1351 | D7: =IFERROR(__xludf.DUMMYFUNCTION("GOOGLEFINANCE(A7,""PRICE"")"),1227.9) -> 1227.9 | E7: =B7*C7 -> 477469 | F7: =C7*D7 -> 1658892.9 | G7: =IFERROR(__xludf.DUMMYFUNCTION("GOOGLEFINANCE(A7,""changepct"")"),-1.4) -> -1.4 | H7: =(D7-B7)/B7 -> 2.4743468 | I7: =F7/F$28 -> 0.093913241 | J7: =F7-E7 -> 1181423.9
A8: NSE:LAURUSLABS | B8: 549.37 | C8: 1120 | D8: =IFERROR(__xludf.DUMMYFUNCTION("GOOGLEFINANCE(A8,""PRICE"")"),1225.2) -> 1225.2 | E8: =B8*C8 -> 615294.4 | F8: =C8*D8 -> 1372224 | G8: =IFERROR(__xludf.DUMMYFUNCTION("GOOGLEFINANCE(A8,""changepct"")"),1.55) -> 1.55 | H8: =(D8-B8)/B8 -> 1.2301909 | I8: =F8/F$28 -> 0.077684342 | J8: =F8-E8 -> 756929.6
A9: NSE:WINDLAS | B9: 807.77333 | C9: 450 | D9: =IFERROR(__xludf.DUMMYFUNCTION("GOOGLEFINANCE(A9,""PRICE"")"),826.0) -> 826 | E9: =B9*C9 -> 363498 | F9: =C9*D9 -> 371700 | G9: =IFERROR(__xludf.DUMMYFUNCTION("GOOGLEFINANCE(A9,""changepct"")"),-3.34) -> -3.34 | H9: =(D9-B9)/B9 -> 0.022564086 | I9: =F9/F$28 -> 0.021042679 | J9: =F9-E9 -> 8202
A10: NSE:ENTERO | B10: 1217.7474 | C10: 475 | D10: =IFERROR(__xludf.DUMMYFUNCTION("GOOGLEFINANCE(A10,""PRICE"")"),1221.0) -> 1221 | E10: =B10*C10 -> 578430 | F10: =C10*D10 -> 579975 | G10: =IFERROR(__xludf.DUMMYFUNCTION("GOOGLEFINANCE(A10,""changepct"")"),-3.53) -> -3.53 | H10: =(D10-B10)/B10 -> 0.0026710302 | I10: =F10/F$28 -> 0.032833543 | J10: =F10-E10 -> 1545.004
A11: NSE:ABCAPITAL | B11: 192 | C11: 1000 | D11: =IFERROR(__xludf.DUMMYFUNCTION("GOOGLEFINANCE(A11,""PRICE"")"),362.3) -> 362.3 | E11: =B11*C11 -> 192000 | F11: =C11*D11 -> 362300 | G11: =IFERROR(__xludf.DUMMYFUNCTION("GOOGLEFINANCE(A11,""changepct"")"),-1.82) -> -1.82 | H11: =(D11-B11)/B11 -> 0.88697917 | I11: =F11/F$28 -> 0.020510527 | J11: =F11-E11 -> 170300
A12: NSE:INTERARCH | B12: 1902 | C12: 250 | D12: =IFERROR(__xludf.DUMMYFUNCTION("GOOGLEFINANCE(A12,""PRICE"")"),2142.5) -> 2142.5 | E12: =B12*C12 -> 475500 | F12: =C12*D12 -> 535625 | G12: =IFERROR(__xludf.DUMMYFUNCTION("GOOGLEFINANCE(A12,""changepct"")"),-1.66) -> -1.66 | H12: =(D12-B12)/B12 -> 0.12644585 | I12: =F12/F$28 -> 0.030322801 | J12: =F12-E12 -> 60125
A13: NSE:UJJIVANSFB | B13: 43.69 | C13: 13000 | D13: =IFERROR(__xludf.DUMMYFUNCTION("GOOGLEFINANCE(A13,""PRICE"")"),62.4) -> 62.4 | E13: =B13*C13 -> 567970 | F13: =C13*D13 -> 811200 | G13: =IFERROR(__xludf.DUMMYFUNCTION("GOOGLEFINANCE(A13,""changepct"")"),-0.43) -> -0.43 | H13: =(D13-B13)/B13 -> 0.42824445 | I13: =F13/F$28 -> 0.045923652 | J13: =F13-E13 -> 243230
A14: NSE:PAYTM | B14: 987.41429 | C14: 350 | D14: =IFERROR(__xludf.DUMMYFUNCTION("GOOGLEFINANCE(A14,""PRICE"")"),1188.0) -> 1188 | E14: =B14*C14 -> 345595 | F14: =C14*D14 -> 415800 | G14: =IFERROR(__xludf.DUMMYFUNCTION("GOOGLEFINANCE(A14,""changepct"")"),-0.79) -> -0.79 | H14: =(D14-B14)/B14 -> 0.20314241 | I14: =F14/F$28 -> 0.023539269 | J14: =F14-E14 -> 70205
A15: NSE:FDC | B15: 490.65 | C15: 2300 | D15: =IFERROR(__xludf.DUMMYFUNCTION("GOOGLEFINANCE(A15,""PRICE"")"),380.25) -> 380.25 | E15: =B15*C15 -> 1128495 | F15: =C15*D15 -> 874575 | G15: =IFERROR(__xludf.DUMMYFUNCTION("GOOGLEFINANCE(A15,""changepct"")"),1.25) -> 1.25 | H15: =(D15-B15)/B15 -> -0.22500764 | I15: =F15/F$28 -> 0.049511438 | J15: =F15-E15 -> -253920
A16: NSE:SILVERBEES | B16: 122 | C16: 800 | D16: =IFERROR(__xludf.DUMMYFUNCTION("GOOGLEFINANCE(A16,""PRICE"")"),240.0) -> 240 | E16: =B16*C16 -> 97600 | F16: =C16*D16 -> 192000 | G16: =IFERROR(__xludf.DUMMYFUNCTION("GOOGLEFINANCE(A16,""changepct"")"),0.23) -> 0.23 | H16: =(D16-B16)/B16 -> 0.96721311 | I16: =F16/F$28 -> 0.010869504 | J16: =F16-E16 -> 94400
A17: NSE:GOLDIETF | B17: 95.15 | C17: 2000 | D17: =IFERROR(__xludf.DUMMYFUNCTION("GOOGLEFINANCE(A17,""PRICE"")"),128.73) -> 128.73 | E17: =B17*C17 -> 190300 | F17: =C17*D17 -> 257460 | G17: =IFERROR(__xludf.DUMMYFUNCTION("GOOGLEFINANCE(A17,""changepct"")"),-0.16) -> -0.16 | H17: =(D17-B17)/B17 -> 0.35291645 | I17: =F17/F$28 -> 0.014575325 | J17: =F17-E17 -> 67160
A18: NSE:CSBBANK | B18: 376.2319 | C18: 2100 | D18: =IFERROR(__xludf.DUMMYFUNCTION("GOOGLEFINANCE(A18,""PRICE"")"),365.0) -> 365 | E18: =B18*C18 -> 790087 | F18: =C18*D18 -> 766500 | G18: =IFERROR(__xludf.DUMMYFUNCTION("GOOGLEFINANCE(A18,""changepct"")"),2.26) -> 2.26 | H18: =(D18-B18)/B18 -> -0.029853674 | I18: =F18/F$28 -> 0.043393096 | J18: =F18-E18 -> -23587
A19: POCL | B19: 1340.71 | C19: 440 | D19: =IFERROR(__xludf.DUMMYFUNCTION("GOOGLEFINANCE(A19,""PRICE"")"),1430.5) -> 1430.5 | E19: =B19*C19 -> 589912.4 | F19: =C19*D19 -> 629420 | G19: =IFERROR(__xludf.DUMMYFUNCTION("GOOGLEFINANCE(A19,""changepct"")"),-0.4) -> -0.4 | H19: =(D19-B19)/B19 -> 0.066971978 | I19: =F19/F$28 -> 0.035632723 | J19: =F19-E19 -> 39507.6
A20: NSE:MCX | B20: =9462.5/5 -> 1892.5 | C20: =120*5 -> 600 | D20: =IFERROR(__xludf.DUMMYFUNCTION("GOOGLEFINANCE(A20,""PRICE"")"),3098.0) -> 3098 | E20: =B20*C20 -> 1135500 | F20: =C20*D20 -> 1858800 | G20: =IFERROR(__xludf.DUMMYFUNCTION("GOOGLEFINANCE(A20,""changepct"")"),1.82) -> 1.82 | H20: =(D20-B20)/B20 -> 0.63698811 | I20: =F20/F$28 -> 0.10523038 | J20: =F20-E20 -> 723300
A21: NSE:ACUTAAS | B21: 1740 | C21: 200 | D21: =IFERROR(__xludf.DUMMYFUNCTION("GOOGLEFINANCE(A21,""PRICE"")"),2745.1) -> 2745.1 | E21: =B21*C21 -> 348000 | F21: =C21*D21 -> 549020 | G21: =IFERROR(__xludf.DUMMYFUNCTION("GOOGLEFINANCE(A21,""changepct"")"),0.71) -> 0.71 | H21: =(D21-B21)/B21 -> 0.57764368 | I21: =F21/F$28 -> 0.031081119 | J21: =F21-E21 -> 201020
A22: NSE:SANSERA | B22: 1701.71 | C22: 188 | D22: =IFERROR(__xludf.DUMMYFUNCTION("GOOGLEFINANCE(A22,""PRICE"")"),2521.8) -> 2521.8 | E22: =B22*C22 -> 319921.48 | F22: =C22*D22 -> 474098.4 | G22: =IFERROR(__xludf.DUMMYFUNCTION("GOOGLEFINANCE(A22,""changepct"")"),-1.03) -> -1.03 | H22: =(D22-B22)/B22 -> 0.48192113 | I22: =F22/F$28 -> 0.026839657 | J22: =F22-E22 -> 154176.92
A23: NSE:AARTIPHARM | B23: 783.33 | C23: 600 | D23: =IFERROR(__xludf.DUMMYFUNCTION("GOOGLEFINANCE(A23,""PRICE"")"),767.0) -> 767 | E23: =B23*C23 -> 469998 | F23: =C23*D23 -> 460200 | G23: =IFERROR(__xludf.DUMMYFUNCTION("GOOGLEFINANCE(A23,""changepct"")"),-1.37) -> -1.37 | H23: =(D23-B23)/B23 -> -0.020846897 | I23: =F23/F$28 -> 0.026052841 | J23: =F23-E23 -> -9798
A24: NSE:SMLMAH | B24: 4395 | C24: 150 | D24: =IFERROR(__xludf.DUMMYFUNCTION("GOOGLEFINANCE(A24,""PRICE"")"),3807.0) -> 3807 | E24: =B24*C24 -> 659250 | F24: =C24*D24 -> 571050 | G24: =IFERROR(__xludf.DUMMYFUNCTION("GOOGLEFINANCE(A24,""changepct"")"),-2.09) -> -2.09 | H24: =(D24-B24)/B24 -> -0.1337884 | I24: =F24/F$28 -> 0.032328281 | J24: =F24-E24 -> -88200
A25: NSE:SONACOMS | B25: 535.795 | C25: 600 | D25: =IFERROR(__xludf.DUMMYFUNCTION("GOOGLEFINANCE(A25,""PRICE"")"),579.65) -> 579.65 | E25: =B25*C25 -> 321477 | F25: =C25*D25 -> 347790 | G25: =IFERROR(__xludf.DUMMYFUNCTION("GOOGLEFINANCE(A25,""changepct"")"),0.17) -> 0.17 | H25: =(D25-B25)/B25 -> 0.081850335 | I25: =F25/F$28 -> 0.019689087 | J25: =F25-E25 -> 26313
A26: NSE:J&KBANK | B26: 115.6 | C26: 3000 | D26: =IFERROR(__xludf.DUMMYFUNCTION("GOOGLEFINANCE(A26,""PRICE"")"),141.1) -> 141.1 | E26: =B26*C26 -> 346800 | F26: =C26*D26 -> 423300 | G26: =IFERROR(__xludf.DUMMYFUNCTION("GOOGLEFINANCE(A31,""changepct"")"),"#N/A") -> #N/A | H26: =(D26-B26)/B26 -> 0.22058824 | I26: =F26/F$28 -> 0.023963858 | J26: =F26-E26 -> 76500
E28: =SUM(E2:E26) -> 12741808 | F28: =SUM(F2:F26) -> 17664100
C31: 44998 | D31: Alwyas remember the following loss | K31: =+K7+K8 -> 0
B32: =A32/350 -> 0 | C32: 15 may for ibreal
D33: ppl | E33: 916134 | F33: got carried away with PE buying at much lower price | J33: 868
D34: pel | E34: 401485 | F34: got carried away with special situation
D35: laurus | E35: 285045 | F35: was not able to predict cyclic nature
D36: ibreal | E36: =964737-570000 -> 394737 | F36: waited for special situations to happen
C38: 45068 | D38: aavas | E38: 195899 | F38: Had lot of coviction on home finance | I38: dynamic promoter left
E40: =E33+E34+E35+E36+E38 -> 2193300 | F40: loss
D41: GMM
D43: new losses made in october sell
D44: krishca | E44: 180000 | F44: think 1000 times before putting into sme space - headwinds against sme was also reason , company was realy good
D45: just dial | E45: 191275 | F45: Sold them as had beeter opportunity ,again not bad company but headwinds were there
D46: EIH | E46: 122325 | F46: Sold them to move to better story Samhi
D47: kirloskar engines | E47: 343877 | F47: was a big mistake .learning is when you have to sell dont wait for price to come back could had easily saved a lakh
D48: Apar | E48: 840000 | F48: was a mistake where i ended up buying more even after bull market started , should had sold after a bad con call whihc clearly showed slow down , should had sold even after ishmohit giving a sell call ,would had easily saved 3 lakhs 7 thousand so always sell when expert says to sell
D49: shivalik rasayan | E49: 600000 | F49: let numbers show like larus as sajals bets needs to be played with some stomach
C50: losses in year 2025
D51: Arvind smart space | E51: 273620 | F51: Its moving too slow and exited as there were better ideas . Could had avoided it
D52: Oswal pumps | E52: 651603 | F52: B2G and signals were pretty clear
C54: losses in year 2026
D55: Intellect design arena | E55: 467252 | F55: IT as a sector or tech was not prefffred , went against sector narrative and bought beacuse of an amzing quarter , false break out also was reason , learning is breakput for a sector whihc is not prefferred should be tighlt managed by stop loss otherwise it will end up you burning fingers .Its ok if you want to sit but there is very high chance of opporunity cost
D56: jayaswal neco | E56: 231022 | F56: market really deteriorated and betting on turn around story seemed little more risky as many better stories started looking very good to buy

Sheet manjari
A1: \ | B1: Stock tikr | C1: Average Buying price | D1: quantity | E1: CMP | F1: Investment | G1: Current value | H1: change today | I1: Over all change | J1: Allocation | K1: Column 1
A2: Neuland | B2: NSE:NEULANDLAB | C2: 1377.5 | D2: 80 | E2: =IFERROR(__xludf.DUMMYFUNCTION("GOOGLEFINANCE(B2,""PRICE"")"),17750.0) -> 17750 | F2: =C2*D2 -> 110200 | G2: =D2*E2 -> 1420000 | H2: =IFERROR(__xludf.DUMMYFUNCTION("GOOGLEFINANCE(B2,""changepct"")"),2.69) -> 2.69 | I2: =(E2-C2)/C2 -> 11.885662 | J2: =G2/G$27 -> 0.087060126
A3: nh | B3: NSE:NH | C3: 724.7678 | D3: 596 | E3: =IFERROR(__xludf.DUMMYFUNCTION("GOOGLEFINANCE(B3,""PRICE"")"),1820.0) -> 1820 | F3: =C3*D3 -> 431961.61 | G3: =D3*E3 -> 1084720 | H3: =IFERROR(__xludf.DUMMYFUNCTION("GOOGLEFINANCE(B3,""changepct"")"),-1.95) -> -1.95 | I3: =(E3-C3)/C3 -> 1.5111491 | J3: =G3/G$27 -> 0.066504127
A4: SAMHI | B4: NSE:SAMHI | C4: 185.48 | D4: 2616 | E4: =IFERROR(__xludf.DUMMYFUNCTION("GOOGLEFINANCE(B4,""PRICE"")"),158.58) -> 158.58 | F4: =C4*D4 -> 485215.68 | G4: =D4*E4 -> 414845.28 | H4: =IFERROR(__xludf.DUMMYFUNCTION("GOOGLEFINANCE(B4,""changepct"")"),0.14) -> 0.14 | I4: =(E4-C4)/C4 -> -0.14502911 | J4: =G4/G$27 -> 0.025434143
A5: JM FINANCIALS | B5: NSE:JMFINANCIL | C5: 135.74074 | D5: 5400 | E5: =IFERROR(__xludf.DUMMYFUNCTION("GOOGLEFINANCE(B5,""PRICE"")"),145.37) -> 145.37 | F5: =C5*D5 -> 733000 | G5: =D5*E5 -> 784998 | H5: =IFERROR(__xludf.DUMMYFUNCTION("GOOGLEFINANCE(B5,""changepct"")"),1.76) -> 1.76 | I5: =(E5-C5)/C5 -> 0.070938608 | J5: =G5/G$27 -> 0.048128187
A6: ABCAPITAL | B6: NSE:ABCAPITAL | C6: 200.83333 | D6: 3000 | E6: =IFERROR(__xludf.DUMMYFUNCTION("GOOGLEFINANCE(B6,""PRICE"")"),362.3) -> 362.3 | F6: =C6*D6 -> 602500 | G6: =D6*E6 -> 1086900 | H6: =IFERROR(__xludf.DUMMYFUNCTION("GOOGLEFINANCE(B6,""changepct"")"),-1.82) -> -1.82 | I6: =(E6-C6)/C6 -> 0.8039834 | J6: =G6/G$27 -> 0.066637782
A7: TDPOWERSYS | B7: NSE:TDPOWERSYS | C7: 414.98 | D7: 2550 | E7: =IFERROR(__xludf.DUMMYFUNCTION("GOOGLEFINANCE(B7,""PRICE"")"),1227.9) -> 1227.9 | F7: =C7*D7 -> 1058199 | G7: =D7*E7 -> 3131145 | H7: =IFERROR(__xludf.DUMMYFUNCTION("GOOGLEFINANCE(B7,""changepct"")"),-1.4) -> -1.4 | I7: =(E7-C7)/C7 -> 1.9589378 | J7: =G7/G$27 -> 0.19197034
A8: SOLARA | B8: NSE:SOLARA | C8: 609.125 | D8: 800 | E8: =IFERROR(__xludf.DUMMYFUNCTION("GOOGLEFINANCE(B8,""PRICE"")"),522.5) -> 522.5 | F8: =C8*D8 -> 487300 | G8: =D8*E8 -> 418000 | H8: =IFERROR(__xludf.DUMMYFUNCTION("GOOGLEFINANCE(B8,""changepct"")"),1.49) -> 1.49 | I8: =(E8-C8)/C8 -> -0.14221219 | J8: =G8/G$27 -> 0.025627558
A9: NSE:LAURUS | B9: NSE:LAURUSLABS | C9: 560 | D9: 550 | E9: =IFERROR(__xludf.DUMMYFUNCTION("GOOGLEFINANCE(B9,""PRICE"")"),1225.2) -> 1225.2 | F9: =C9*D9 -> 308000 | G9: =D9*E9 -> 673860 | H9: =IFERROR(__xludf.DUMMYFUNCTION("GOOGLEFINANCE(B9,""changepct"")"),1.55) -> 1.55 | I9: =(E9-C9)/C9 -> 1.1878571 | J9: =G9/G$27 -> 0.041314322
A10: NSE:ENTERO | B10: NSE:ENTERO | C10: 1203.87 | D10: 546 | E10: =IFERROR(__xludf.DUMMYFUNCTION("GOOGLEFINANCE(B10,""PRICE"")"),1221.0) -> 1221 | F10: =C10*D10 -> 657313.02 | G10: =D10*E10 -> 666666 | H10: =IFERROR(__xludf.DUMMYFUNCTION("GOOGLEFINANCE(B10,""changepct"")"),-3.53) -> -3.53 | I10: =(E10-C10)/C10 -> 0.014229111 | J10: =G10/G$27 -> 0.040873258
A11: NSE:INTERARCH | B11: NSE:INTERARCH | C11: 1845 | D11: 200 | E11: =IFERROR(__xludf.DUMMYFUNCTION("GOOGLEFINANCE(B11,""PRICE"")"),2142.5) -> 2142.5 | F11: =C11*D11 -> 369000 | G11: =D11*E11 -> 428500 | H11: =IFERROR(__xludf.DUMMYFUNCTION("GOOGLEFINANCE(B11,""changepct"")"),-1.66) -> -1.66 | I11: =(E11-C11)/C11 -> 0.16124661 | J11: =G11/G$27 -> 0.026271313
A12: NSE:PAYTM | B12: NSE:PAYTM | C12: 961.72167 | D12: 250 | E12: =IFERROR(__xludf.DUMMYFUNCTION("GOOGLEFINANCE(B12,""PRICE"")"),1188.0) -> 1188 | F12: =C12*D12 -> 240430.42 | G12: =D12*E12 -> 297000 | H12: =IFERROR(__xludf.DUMMYFUNCTION("GOOGLEFINANCE(B12,""changepct"")"),-0.79) -> -0.79 | I12: =(E12-C12)/C12 -> 0.23528464 | J12: =G12/G$27 -> 0.018209055
A13: NSE:UJJIVAN | B13: NSE:UJJIVANSFB | C13: 43.77 | D13: 13000 | E13: =IFERROR(__xludf.DUMMYFUNCTION("GOOGLEFINANCE(B13,""PRICE"")"),62.4) -> 62.4 | F13: =C13*D13 -> 569010 | G13: =D13*E13 -> 811200 | H13: =IFERROR(__xludf.DUMMYFUNCTION("GOOGLEFINANCE(B13,""changepct"")"),-0.43) -> -0.43 | I13: =(E13-C13)/C13 -> 0.425634 | J13: =G13/G$27 -> 0.04973463
A14: NSE:FDC | B14: NSE:FDC | C14: 464.95714 | D14: 1400 | E14: =IFERROR(__xludf.DUMMYFUNCTION("GOOGLEFINANCE(B14,""PRICE"")"),380.25) -> 380.25 | F14: =C14*D14 -> 650940 | G14: =D14*E14 -> 532350 | H14: =IFERROR(__xludf.DUMMYFUNCTION("GOOGLEFINANCE(B14,""changepct"")"),1.25) -> 1.25 | I14: =(E14-C14)/C14 -> -0.18218269 | J14: =G14/G$27 -> 0.032638351
A15: NSE:SILVERBEES | B15: NSE:SILVERBEES | C15: 122 | D15: 800 | E15: =IFERROR(__xludf.DUMMYFUNCTION("GOOGLEFINANCE(B15,""PRICE"")"),240.0) -> 240 | F15: =C15*D15 -> 97600 | G15: =D15*E15 -> 192000 | H15: =IFERROR(__xludf.DUMMYFUNCTION("GOOGLEFINANCE(B15,""changepct"")"),0.23) -> 0.23 | I15: =(E15-C15)/C15 -> 0.96721311 | J15: =G15/G$27 -> 0.01177151
A16: NSE:GOLDIETF | B16: NSE:GOLDIETF | C16: 96.38 | D16: 1000 | E16: =IFERROR(__xludf.DUMMYFUNCTION("GOOGLEFINANCE(B16,""PRICE"")"),128.73) -> 128.73 | F16: =C16*D16 -> 96380 | G16: =D16*E16 -> 128730 | H16: =IFERROR(__xludf.DUMMYFUNCTION("GOOGLEFINANCE(B16,""changepct"")"),-0.16) -> -0.16 | I16: =(E16-C16)/C16 -> 0.33565055 | J16: =G16/G$27 -> 0.0078924296
A17: NSE:CSBBANK | B17: NSE:CSBBANK | C17: 378.58824 | D17: 1700 | E17: =IFERROR(__xludf.DUMMYFUNCTION("GOOGLEFINANCE(B17,""PRICE"")"),365.0) -> 365 | F17: =C17*D17 -> 643600 | G17: =D17*E17 -> 620500 | H17: =IFERROR(__xludf.DUMMYFUNCTION("GOOGLEFINANCE(B17,""changepct"")"),2.26) -> 2.26 | I17: =(E17-C17)/C17 -> -0.035891858 | J17: =G17/G$27 -> 0.038042823
A18: NSE:POCL | B18: NSE:POCL | C18: 1337.63 | D18: 283 | E18: =IFERROR(__xludf.DUMMYFUNCTION("GOOGLEFINANCE(B18,""PRICE"")"),1430.5) -> 1430.5 | F18: =C18*D18 -> 378549.29 | G18: =D18*E18 -> 404831.5 | H18: =IFERROR(__xludf.DUMMYFUNCTION("GOOGLEFINANCE(B18,""changepct"")"),-0.4) -> -0.4 | I18: =(E18-C18)/C18 -> 0.069428766 | J18: =G18/G$27 -> 0.024820198
A19: NSE:MCX | B19: NSE:MCX | C19: =9444.047619/5 -> 1888.8095 | D19: =84*5 -> 420 | E19: =IFERROR(__xludf.DUMMYFUNCTION("GOOGLEFINANCE(B19,""PRICE"")"),3098.0) -> 3098 | F19: =C19*D19 -> 793300 | G19: =D19*E19 -> 1301160 | H19: =IFERROR(__xludf.DUMMYFUNCTION("GOOGLEFINANCE(B19,""changepct"")"),1.82) -> 1.82 | I19: =(E19-C19)/C19 -> 0.64018656 | J19: =G19/G$27 -> 0.079774052
A20: NSE:ACUTAAS | B20: NSE:ACUTAAS | C20: 1700 | D20: 100 | E20: =IFERROR(__xludf.DUMMYFUNCTION("GOOGLEFINANCE(B20,""PRICE"")"),2745.1) -> 2745.1 | F20: =C20*D20 -> 170000 | G20: =D20*E20 -> 274510 | H20: =IFERROR(__xludf.DUMMYFUNCTION("GOOGLEFINANCE(B20,""changepct"")"),0.71) -> 0.71 | I20: =(E20-C20)/C20 -> 0.61476471 | J20: =G20/G$27 -> 0.016830194
A21: NSE:SANSERA | B21: NSE:SANSERA | C21: 1697.19 | D21: 180 | E21: =IFERROR(__xludf.DUMMYFUNCTION("GOOGLEFINANCE(B21,""PRICE"")"),2521.8) -> 2521.8 | F21: =C21*D21 -> 305494.2 | G21: =D21*E21 -> 453924 | H21: =IFERROR(__xludf.DUMMYFUNCTION("GOOGLEFINANCE(B21,""changepct"")"),-1.03) -> -1.03 | I21: =(E21-C21)/C21 -> 0.48586782 | J21: =G21/G$27 -> 0.027830057
A22: NSE:AARTIPHARM | B22: NSE:AARTIPHARM | C22: 780.83 | D22: 600 | E22: =IFERROR(__xludf.DUMMYFUNCTION("GOOGLEFINANCE(B22,""PRICE"")"),767.0) -> 767 | F22: =C22*D22 -> 468498 | G22: =D22*E22 -> 460200 | H22: =IFERROR(__xludf.DUMMYFUNCTION("GOOGLEFINANCE(B22,""changepct"")"),-1.37) -> -1.37 | I22: =(E22-C22)/C22 -> -0.017711922 | J22: =G22/G$27 -> 0.028214838
A23: NSE:SONACOMS | B23: NSE:SONACOMS | C23: 535.52 | D23: 600 | E23: =IFERROR(__xludf.DUMMYFUNCTION("GOOGLEFINANCE(B23,""PRICE"")"),579.65) -> 579.65 | F23: =C23*D23 -> 321312 | G23: =D23*E23 -> 347790 | H23: =IFERROR(__xludf.DUMMYFUNCTION("GOOGLEFINANCE(B23,""changepct"")"),0.17) -> 0.17 | I23: =(E23-C23)/C23 -> 0.082405886 | J23: =G23/G$27 -> 0.021322987
A24: J&KBANK | B24: NSE:J&KBANK | C24: 115.78 | D24: 2670 | E24: =IFERROR(__xludf.DUMMYFUNCTION("GOOGLEFINANCE(B24,""PRICE"")"),141.1) -> 141.1 | F24: =C24*D24 -> 309132.6 | G24: =D24*E24 -> 376737 | H24: =IFERROR(__xludf.DUMMYFUNCTION("GOOGLEFINANCE(B24,""changepct"")"),1.05) -> 1.05 | I24: =(E24-C24)/C24 -> 0.21869062 | J24: =G24/G$27 -> 0.023097726
F27: =SUM(F2:F24) -> 10286936 | G27: =SUM(G2:G24) -> 16310567

Sheet MANJBHAWNA
A1: Stock tikr | B1: Average Buying price | C1: quantity | D1: CMP | E1: Investment | F1: Current value | G1: change today | H1: Over all change | I1: Allocation | J1: Column 1
A2: NSE:TDPOWERSYS | B2: 410 | C2: 350 | D2: =IFERROR(__xludf.DUMMYFUNCTION("GOOGLEFINANCE(A2,""PRICE"")"),1227.9) -> 1227.9 | E2: =B2*C2 -> 143500 | F2: =C2*D2 -> 429765 | G2: =IFERROR(__xludf.DUMMYFUNCTION("GOOGLEFINANCE(A2,""changepct"")"),-1.4) -> -1.4 | H2: =(D2-B2)/B2 -> 1.994878 | I2: =F2/F$9*100 -> 23.449483 | J2: =F2-E2 -> 286265
A3: NSE:GOLDBEES | B3: 124.39 | C3: 3000 | D3: =IFERROR(__xludf.DUMMYFUNCTION("GOOGLEFINANCE(A3,""PRICE"")"),124.39) -> 124.39 | E3: =B3*C3 -> 373170 | F3: =C3*D3 -> 373170 | G3: =IFERROR(__xludf.DUMMYFUNCTION("GOOGLEFINANCE(A3,""changepct"")"),-0.06) -> -0.06 | H3: =(D3-B3)/B3 -> 0 | I3: =F3/F$9*100 -> 20.361461 | J3: =F3-E3 -> 0
A4: NSE:AARTIPHARM | B4: 760 | C4: 161 | D4: =IFERROR(__xludf.DUMMYFUNCTION("GOOGLEFINANCE(A4,""PRICE"")"),767.0) -> 767 | E4: =B4*C4 -> 122360 | F4: =C4*D4 -> 123487 | G4: =IFERROR(__xludf.DUMMYFUNCTION("GOOGLEFINANCE(A4,""changepct"")"),-1.37) -> -1.37 | H4: =(D4-B4)/B4 -> 0.0092105263 | I4: =F4/F$9*100 -> 6.7378829 | J4: =F4-E4 -> 1127
A5: NSE:CSBBANK | B5: 420.44 | C5: 410 | D5: =IFERROR(__xludf.DUMMYFUNCTION("GOOGLEFINANCE(A5,""PRICE"")"),365.0) -> 365 | E5: =B5*C5 -> 172380.4 | F5: =C5*D5 -> 149650 | G5: =IFERROR(__xludf.DUMMYFUNCTION("GOOGLEFINANCE(A5,""changepct"")"),2.26) -> 2.26 | H5: =(D5-B5)/B5 -> -0.13186186 | I5: =F5/F$9*100 -> 8.1654278 | J5: =F5-E5 -> -22730.4
A6: NSE:MCX | B6: 2190 | C6: 135 | D6: =IFERROR(__xludf.DUMMYFUNCTION("GOOGLEFINANCE(A6,""PRICE"")"),3098.0) -> 3098 | E6: =B6*C6 -> 295650 | F6: =C6*D6 -> 418230 | G6: =IFERROR(__xludf.DUMMYFUNCTION("GOOGLEFINANCE(A6,""changepct"")"),1.82) -> 1.82 | H6: =(D6-B6)/B6 -> 0.41461187 | I6: =F6/F$9*100 -> 22.820093 | J6: =F6-E6 -> 122580
A7: NSE:SOLARA | B7: 512 | C7: 170 | D7: =IFERROR(__xludf.DUMMYFUNCTION("GOOGLEFINANCE(A7,""PRICE"")"),522.5) -> 522.5 | E7: =B7*C7 -> 87040 | F7: =C7*D7 -> 88825 | G7: =IFERROR(__xludf.DUMMYFUNCTION("GOOGLEFINANCE(A7,""changepct"")"),1.49) -> 1.49 | H7: =(D7-B7)/B7 -> 0.020507812 | I7: =F7/F$9*100 -> 4.8466029 | J7: =F7-E7 -> 1785
A8: NSE:UJJIVANSFB | B8: 44.5 | C8: 4000 | D8: =IFERROR(__xludf.DUMMYFUNCTION("GOOGLEFINANCE(A8,""PRICE"")"),62.4) -> 62.4 | E8: =B8*C8 -> 178000 | F8: =C8*D8 -> 249600 | G8: =IFERROR(__xludf.DUMMYFUNCTION("GOOGLEFINANCE(A8,""changepct"")"),-0.43) -> -0.43 | H8: =(D8-B8)/B8 -> 0.40224719 | I8: =F8/F$9*100 -> 13.61905 | J8: =F8-E8 -> 71600
E9: =SUM(E2:E8) -> 1372100.4 | F9: =SUM(F2:F8) -> 1832727
F10: 1.86 | G10: CASH | J10: =484*400 -> 193600 | K10: =J11+J10 -> 388600
J11: =390*500 -> 195000
B12: bull | C12: exit pe | D12: base | E12: exit pe | F12: bear | G12: exit pe | H12: current pe
A13: senco | B13: 28.27 | C13: 40 | D13: 19.98 | E13: 35 | F13: 11.08 | G13: 30
A14: medassist | B14: 21.31 | C14: 40 | D14: 15.53 | E14: 35 | F14: 9.11 | G14: 30
A15: indigo | B15: 45.36 | C15: 25 | D15: 27.92 | E15: 22 | F15: 16.29 | G15: 20
A16: equitas | B16: 45.47 | C16: 3x | D16: 32.8 | E16: 2.5x | F16: 18.78 | G16: 2x
A17: racl | B17: 66.29 | C17: 30 | D17: 38.57 | E17: 25 | F17: 10.86 | G17: 20
A18: venus | B18: 26.21 | C18: 35 | D18: 16.85 | E18: 30 | F18: 6.67 | G18: 25
A19: samhi | B19: 36.61 | C19: 18 | D19: 27.56 | E19: 16 | F19: 22.78 | G19: 15
A20: glenmark | B20: 28.58 | C20: 30 | D20: 24.22 | E20: 28 | F20: 17.37 | G20: 25
A21: polycab | B21: 16.84 | C21: 50 | D21: 10.85 | E21: 45 | F21: 4.51 | G21: 40
A22: pennar | B22: 30.22 | C22: 20 | D22: 23.54 | E22: 18 | F22: 12.78 | G22: 15
A23: marksans | B23: 31.28 | C23: 25 | D23: 23.15 | E23: 22 | F23: 17.42 | G23: 20 | H23: 23.2
A24: time technoplast | B24: 30.97 | C24: 22 | D24: 24.87 | E24: 20 | F24: 18.46 | G24: 18
A25: sandhar | B25: 48.32 | C25: 25 | D25: 30.53 | E25: 22 | F25: 18.66 | G25: 20

Sheet consolidated
A1: Stock tikr | B1: Stock tikr 2 | C1: Average Buying price | D1: quantity | E1: CMP | F1: MARKET CAP | G1: Invested Amount | H1: Current Value | I1: Date of Buy | J1: Profit | K1: Allocation % | L1: Allocation % 2 | M1: PE | N1: Allowed drawdown | O1: Allowed Price | P1: Max Price | Q1: Column 17 | Y1: Hotels | AB1: cash | AC1: 0
A2: neuland | B2: NSE:NEULANDLAB | C2: =((vibhanshu!C2*vibhanshu!D2)+(manjari!C2*manjari!D2)+(HUF!B3*HUF!C3))/D2 -> 2699.5652 | D2: =vibhanshu!D2+manjari!D2+HUF!C3 -> 230 | E2: =IFERROR(__xludf.DUMMYFUNCTION("GOOGLEFINANCE(B2,""PRICE"")"),17750.0) -> 17750 | F2: =IFERROR(__xludf.DUMMYFUNCTION("GOOGLEFINANCE(B2,""MARKETCAP"")/10000000"),22773.037) -> 22773.037 | G2: =C2*D2 -> 620900 | H2: =E2*D2 -> 4082500 | J2: =(E2-C2)/C2 -> 5.5751329 | K2: =H2/H$46 -> 0.08102321 | L2: =H2/H$46 -> 0.08102321 | M2: =IFERROR(__xludf.DUMMYFUNCTION("GOOGLEFINANCE(B2,""pe"")"),127.13) -> 127.13 | N2: =if((P2*D2-F$49)<0,0,((P2*D2)-F$49)) -> 4071810 | O2: =N2/D2 -> 17703.522 | P2: =IFERROR(__xludf.DUMMYFUNCTION("index(sortn(GoogleFinance(B2,""high"",DATE(2020,1,1), TODAY(),""DAILY""),2,1,2,0),2,2)"),19747.0) -> 19747 | Q2: =IF(E2>O2,true,false) -> TRUE | V2: CHEMICALS | Y2: samhi | Z2: =K4 -> 0.016809479 | AB2: NEULAND | AC2: 1 | AD2: =T20 -> 0.08102321
A3: nh(6.1) | B3: NSE:NH | C3: =((vibhanshu!C3*vibhanshu!D3)+(manjari!C3*manjari!D3)+(HUF!B2*HUF!C2))/D3 -> 765.07969 | D3: =vibhanshu!D3+manjari!D3+HUF!C2 -> 1846 | E3: =IFERROR(__xludf.DUMMYFUNCTION("GOOGLEFINANCE(B3,""PRICE"")"),1820.0) -> 1820 | F3: =IFERROR(__xludf.DUMMYFUNCTION("GOOGLEFINANCE(B3,""MARKETCAP"")/10000000"),36964.1636) -> 36964.164 | G3: =C3*D3 -> 1412337.1 | H3: =E3*D3 -> 3359720 | J3: =(E3-C3)/C3 -> 1.3788372 | K3: =H3/H$46 -> 0.066678579 | L3: =H3/H$46 -> 0.066678579 | M3: =IFERROR(__xludf.DUMMYFUNCTION("GOOGLEFINANCE(B3,""pe"")"),47.38) -> 47.38 | N3: =if((P3*D3-F$49)<0,0,((P3*D3)-F$49)) -> 3905389.2 | O3: =N3/D3 -> 2115.5954 | P3: =IFERROR(__xludf.DUMMYFUNCTION("index(sortn(GoogleFinance(B3,""high"",DATE(2020,1,1), TODAY(),""DAILY""),2,1,2,0),2,2)"),2370.2) -> 2370.2 | Q3: =IF(E3>O3,true,false) -> FALSE | S3: SFB | T3: =T9+T5 -> 0.044583108 | AB3: NH | AC3: =AC2+1 -> 2 | AD3: =Z11 -> 0.066678579
A4: SAMHI(5.8) | B4: NSE:SAMHI | C4: =((manjari!D4*manjari!C4)+(HUF!C4*HUF!B4))/D4 -> 186.07572 | D4: =HUF!C4+manjari!D4 -> 5341 | E4: =IFERROR(__xludf.DUMMYFUNCTION("GOOGLEFINANCE(B4,""PRICE"")"),158.58) -> 158.58 | F4: =IFERROR(__xludf.DUMMYFUNCTION("GOOGLEFINANCE(B4,""MARKETCAP"")/10000000"),3522.6121132) -> 3522.6121 | G4: =C4*D4 -> 993830.41 | H4: =E4*D4 -> 846975.78 | I4: 45352 | J4: =(E4-C4)/C4 -> -0.14776629 | K4: =H4/H$46 -> 0.016809479 | L4: =H4/H$46 -> 0.016809479 | M4: =IFERROR(__xludf.DUMMYFUNCTION("GOOGLEFINANCE(B4,""pe"")"),16.62) -> 16.62 | N4: =if((P4*D4-F$49)<0,0,((P4*D4)-F$49)) -> 889284.5 | O4: =N4/D4 -> 166.5015 | P4: =IFERROR(__xludf.DUMMYFUNCTION("index(sortn(GoogleFinance(B4,""high"",DATE(2020,1,1), TODAY(),""DAILY""),2,1,2,0),2,2)"),254.5) -> 254.5 | Q4: =IF(E4>O4,true,false) -> FALSE | S4: NBFC | T4: =T8+T7 -> 0.083681645 | Z4: =SUM(Z2:Z3) -> 0.016809479 | AB4: SAMHI | AC4: =AC3+1 -> 3 | AD4: =Z4 -> 0.016809479
A5: JMFINANCIALS(4.3) | B5: NSE:JMFINANCIL | C5: =((vibhanshu!C4*vibhanshu!D4)+(manjari!C5*manjari!D5)+(HUF!B5*HUF!C5))/D5 -> 134.80569 | D5: =manjari!D5+vibhanshu!D4+HUF!C5 -> 15180 | E5: =IFERROR(__xludf.DUMMYFUNCTION("GOOGLEFINANCE(B5,""PRICE"")"),145.37) -> 145.37 | F5: =IFERROR(__xludf.DUMMYFUNCTION("GOOGLEFINANCE(B5,""MARKETCAP"")/10000000"),13904.1486823) -> 13904.149 | G5: =C5*D5 -> 2046350.3 | H5: =E5*D5 -> 2206716.6 | I5: 45566 | J5: =(E5-C5)/C5 -> 0.078366983 | K5: =H5/H$46 -> 0.043795533 | L5: =H5/H$46 -> 0.043795533 | M5: =IFERROR(__xludf.DUMMYFUNCTION("GOOGLEFINANCE(B5,""pe"")"),11.16) -> 11.16 | N5: =if((P5*D5-F$49)<0,0,((P5*D5)-F$49)) -> 2562964 | O5: =N5/D5 -> 168.83821 | P5: =IFERROR(__xludf.DUMMYFUNCTION("index(sortn(GoogleFinance(B5,""high"",DATE(2020,1,1), TODAY(),""DAILY""),2,1,2,0),2,2)"),199.8) -> 199.8 | Q5: =IF(E5>O5,true,false) -> FALSE | AB5: LAURUS | AC5: =AC4+1 -> 4 | AD5: =T19 -> 0.079756132
A6: WINDLAS(2.4) | B6: NSE:WINDLAS | C6: =((vibhanshu!C6*vibhanshu!D6)+(HUF!B9*HUF!C9))/D6 -> 923.47437 | D6: =vibhanshu!D6+HUF!C9 -> 1580 | E6: =IFERROR(__xludf.DUMMYFUNCTION("GOOGLEFINANCE(B6,""PRICE"")"),826.0) -> 826 | F6: =IFERROR(__xludf.DUMMYFUNCTION("GOOGLEFINANCE(B6,""MARKETCAP"")/10000000"),1745.009353) -> 1745.0094 | G6: =C6*D6 -> 1459089.5 | H6: =E6*D6 -> 1305080 | I6: 45597 | J6: =(E6-C6)/C6 -> -0.10555178 | K6: =H6/H$46 -> 0.02590123 | L6: =H6/H$46 -> 0.02590123 | M6: =IFERROR(__xludf.DUMMYFUNCTION("GOOGLEFINANCE(B6,""pe"")"),26.26) -> 26.26 | N6: =if((P6*D6-F$49)<0,0,((P6*D6)-F$49)) -> 1423235 | O6: =N6/D6 -> 900.78165 | P6: =IFERROR(__xludf.DUMMYFUNCTION("index(sortn(GoogleFinance(B6,""high"",DATE(2020,1,1), TODAY(),""DAILY""),2,1,2,0),2,2)"),1198.25) -> 1198.25 | Q6: =IF(E6>O6,true,false) -> FALSE | S6: JM FINANCIALS | T6: =K5 -> 0.043795533 | W6: =SUM(W3:W4) -> 0 | Y6: AUTO ANC | AB6: UJJIVAN | AC6: =AC5+1 -> 5 | AD6: =T9 -> 0.044583108
A7: SOLARA(sajal) | B7: NSE:SOLARA | C7: =((vibhanshu!C5*vibhanshu!D5)+(manjari!C8*manjari!D8)+(HUF!B6*HUF!C6))/D7 -> 635.97224 | D7: =manjari!D8+vibhanshu!D5+HUF!C6 -> 2422 | E7: =IFERROR(__xludf.DUMMYFUNCTION("GOOGLEFINANCE(B7,""PRICE"")"),522.5) -> 522.5 | F7: =IFERROR(__xludf.DUMMYFUNCTION("GOOGLEFINANCE(B7,""MARKETCAP"")/10000000"),2266.1208784) -> 2266.1209 | G7: =C7*D7 -> 1540324.8 | H7: =E7*D7 -> 1265495 | I7: 45598 | J7: =(E7-C7)/C7 -> -0.17842326 | K7: =H7/H$46 -> 0.025115607 | L7: =H7/H$46 -> 0.025115607 | M7: =IFERROR(__xludf.DUMMYFUNCTION("GOOGLEFINANCE(B7,""pe"")"),"#N/A") -> #N/A | N7: =if((P7*D7-F$49)<0,0,((P7*D7)-F$49)) -> 1394940 | O7: =N7/D7 -> 575.9455 | P7: 770 | Q7: =IF(E7>O7,true,false) -> FALSE | S7: AB CAPITAL | T7: =K8 -> 0.046737442 | V7: METALS | AB7: TDPOWER | AC7: =AC6+1 -> 6 | AD7: =Z45 -> 0.1207264
A8: ABCAPITAL(5.9) | B8: NSE:ABCAPITAL | C8: =((vibhanshu!C7*vibhanshu!D7)+(manjari!C6*manjari!D6)+(HUF!B11*HUF!C11))/D8 -> 198.92308 | D8: =vibhanshu!D7+manjari!D6+HUF!C11 -> 6500 | E8: =IFERROR(__xludf.DUMMYFUNCTION("GOOGLEFINANCE(B8,""PRICE"")"),362.3) -> 362.3 | F8: =IFERROR(__xludf.DUMMYFUNCTION("GOOGLEFINANCE(B8,""MARKETCAP"")/10000000"),94679.1528265) -> 94679.153 | G8: =C8*D8 -> 1293000 | H8: =E8*D8 -> 2354950 | I8: 45597 | J8: =(E8-C8)/C8 -> 0.82130704 | K8: =H8/H$46 -> 0.046737442 | L8: =H8/H$46 -> 0.046737442 | M8: =IFERROR(__xludf.DUMMYFUNCTION("GOOGLEFINANCE(B8,""pe"")"),25.44) -> 25.44 | N8: =if((P8*D8-F$49)<0,0,((P8*D8)-F$49)) -> 1973675 | O8: =N8/D8 -> 303.64231 | P8: =IFERROR(__xludf.DUMMYFUNCTION("index(sortn(GoogleFinance(B8,""high"",DATE(2020,1,1), TODAY(),""DAILY""),2,1,2,0),2,2)"),375.95) -> 375.95 | Q8: =IF(E8>O8,true,false) -> TRUE | S8: csb bank | T8: =K18 -> 0.036944202 | V8: JAYNECO | W8: =#REF! -> #REF! | AB8: JM FINANCIALS | AC8: =AC7+1 -> 7 | AD8: =T6 -> 0.043795533
A9: TDPOWERSYS(5.4) | B9: NSE:TDPOWERSYS | C9: =((manjari!C7*manjari!D7)+(vibhanshu!C8*vibhanshu!D8)+(HUF!B7*HUF!C7))/D9 -> 399.50652 | D9: =vibhanshu!D8+manjari!D7+HUF!C7 -> 4954 | E9: =IFERROR(__xludf.DUMMYFUNCTION("GOOGLEFINANCE(B9,""PRICE"")"),1227.9) -> 1227.9 | F9: =IFERROR(__xludf.DUMMYFUNCTION("GOOGLEFINANCE(B9,""MARKETCAP"")/10000000"),19183.2856174) -> 19183.286 | G9: =C9*D9 -> 1979155.3 | H9: =E9*D9 -> 6083016.6 | I9: 45599 | J9: =(E9-C9)/C9 -> 2.0735418 | K9: =H9/H$46 -> 0.1207264 | L9: =H9/H$46 -> 0.1207264 | M9: =IFERROR(__xludf.DUMMYFUNCTION("GOOGLEFINANCE(B9,""pe"")"),87.37) -> 87.37 | N9: =if((P9*D9-F$49)<0,0,((P9*D9)-F$49)) -> 5916696.8 | O9: =N9/D9 -> 1194.3272 | P9: =IFERROR(__xludf.DUMMYFUNCTION("index(sortn(GoogleFinance(B9,""high"",DATE(2020,1,1), TODAY(),""DAILY""),2,1,2,0),2,2)"),1289.2) -> 1289.2 | Q9: =IF(E9>O9,true,false) -> TRUE | S9: UJJIVAN SFB | T9: =K14 -> 0.044583108 | Z9: =SUM(Z7:Z8) -> 0 | AB9: PEB | AC9: =AC8+1 -> 8 | AD9: =W24 -> 0.027766252
A10: LAURUS(sajal) | B10: NSE:LAURUSLABS | C10: =((vibhanshu!C9*vibhanshu!D9)+(manjari!C9*manjari!D9)+(HUF!B8*HUF!C8))/D10 -> 571.02713 | D10: =vibhanshu!D9+HUF!C8+manjari!D9 -> 3280 | E10: =IFERROR(__xludf.DUMMYFUNCTION("GOOGLEFINANCE(B10,""PRICE"")"),1225.2) -> 1225.2 | F10: =IFERROR(__xludf.DUMMYFUNCTION("GOOGLEFINANCE(B10,""MARKETCAP"")/10000000"),66276.9420777) -> 66276.942 | G10: =C10*D10 -> 1872969 | H10: =E10*D10 -> 4018656 | I10: 45658 | J10: =(E10-C10)/C10 -> 1.1456073 | K10: =H10/H$46 -> 0.079756132 | L10: =H10/H$46 -> 0.079756132 | M10: =IFERROR(__xludf.DUMMYFUNCTION("GOOGLEFINANCE(B10,""pe"")"),74.57) -> 74.57 | N10: =if((P10*D10-F$49)<0,0,((P10*D10)-F$49)) -> 3590312 | O10: =N10/D10 -> 1094.6073 | P10: =IFERROR(__xludf.DUMMYFUNCTION("index(sortn(GoogleFinance(B10,""high"",DATE(2020,1,1), TODAY(),""DAILY""),2,1,2,0),2,2)"),1237.9) -> 1237.9 | Q10: =IF(E10>O10,true,false) -> TRUE | T10: =SUM(T5:T9) -> 0.17206029 | Y10: HOSP AND DIAGNOSTICS | AB10: AB CAPITAL | AC10: =AC9+1 -> 9 | AD10: =T4 -> 0.083681645
A11: ENTERO(4.6) | B11: NSE:ENTERO | C11: =((manjari!C10*manjari!D10)+(HUF!B10*HUF!C10)+(vibhanshu!C10*vibhanshu!D10))/D11 -> 1195.1178 | D11: =manjari!D10+HUF!C10+vibhanshu!D10 -> 1520 | E11: =IFERROR(__xludf.DUMMYFUNCTION("GOOGLEFINANCE(B11,""PRICE"")"),1221.0) -> 1221 | F11: =IFERROR(__xludf.DUMMYFUNCTION("GOOGLEFINANCE(B11,""MARKETCAP"")/10000000"),5312.684553) -> 5312.6846 | G11: =C11*D11 -> 1816579 | H11: =E11*D11 -> 1855920 | I11: 45689 | J11: =(E11-C11)/C11 -> 0.021656632 | K11: =H11/H$46 -> 0.036833459 | L11: =H11/H$46 -> 0.036833459 | M11: =IFERROR(__xludf.DUMMYFUNCTION("GOOGLEFINANCE(B11,""pe"")"),47.22) -> 47.22 | N11: =if((P11*D11-F$49)<0,0,((P11*D11)-F$49)) -> 1938060 | O11: =N11/D11 -> 1275.0395 | P11: =IFERROR(__xludf.DUMMYFUNCTION("index(sortn(GoogleFinance(B11,""high"",DATE(2020,1,1), TODAY(),""DAILY""),2,1,2,0),2,2)"),1584.25) -> 1584.25 | Q11: =IF(E11>O11,true,false) -> FALSE | S11: IT | W11: =SUM(W8:W10) -> #REF! | Y11: NH | Z11: =K3 -> 0.066678579 | AB11: FDC | AC11: =AC10+1 -> 10 | AD11: =K15 -> 0.027922494
A12: INTERARCH(3.8) | B12: NSE:INTERARCH | C12: =((manjari!C11*manjari!D11)+(HUF!B12*HUF!C12)+(vibhanshu!C11*vibhanshu!D11))/D12 -> 1860.243 | D12: =manjari!D11+vibhanshu!D11+HUF!C12 -> 653 | E12: =IFERROR(__xludf.DUMMYFUNCTION("GOOGLEFINANCE(B12,""PRICE"")"),2142.5) -> 2142.5 | F12: =IFERROR(__xludf.DUMMYFUNCTION("GOOGLEFINANCE(B12,""MARKETCAP"")/10000000"),3593.3688625) -> 3593.3689 | G12: =C12*D12 -> 1214738.7 | H12: =E12*D12 -> 1399052.5 | I12: 45694 | J12: =(E12-C12)/C12 -> 0.15173126 | K12: =H12/H$46 -> 0.027766252 | L12: =H12/H$46 -> 0.027766252 | M12: =IFERROR(__xludf.DUMMYFUNCTION("GOOGLEFINANCE(B12,""pe"")"),26.57) -> 26.57 | N12: =if((P12*D12-F$49)<0,0,((P12*D12)-F$49)) -> 1333977.8 | O12: =N12/D12 -> 2042.845 | P12: =IFERROR(__xludf.DUMMYFUNCTION("index(sortn(GoogleFinance(B12,""high"",DATE(2020,1,1), TODAY(),""DAILY""),2,1,2,0),2,2)"),2762.6) -> 2762.6 | Q12: =IF(E12>O12,true,false) -> TRUE | V12: CV | Y12: HCG | Z12: =#REF! -> #REF! | AB12: SOLARA | AC12: =AC11+1 -> 11 | AD12: =K7 -> 0.025115607
A13: PAYTM(4.5) | B13: NSE:PAYTM | C13: =((manjari!C12*manjari!D12)+(HUF!B14*HUF!C14)+(vibhanshu!C12*vibhanshu!D12))/D13 -> 970.38824 | D13: =manjari!D12+vibhanshu!D12+HUF!C14 -> 900 | E13: =IFERROR(__xludf.DUMMYFUNCTION("GOOGLEFINANCE(B13,""PRICE"")"),1188.0) -> 1188 | F13: =IFERROR(__xludf.DUMMYFUNCTION("GOOGLEFINANCE(B13,""MARKETCAP"")/10000000"),75733.7049491) -> 75733.705 | G13: =C13*D13 -> 873349.42 | H13: =E13*D13 -> 1069200 | I13: 45695 | J13: =(E13-C13)/C13 -> 0.22425226 | K13: =H13/H$46 -> 0.021219845 | L13: =H13/H$46 -> 0.021219845 | M13: =IFERROR(__xludf.DUMMYFUNCTION("GOOGLEFINANCE(B13,""pe"")"),"#N/A") -> #N/A | N13: =if((P13*D13-F$49)<0,0,((P13*D13)-F$49)) -> 1289500 | O13: =N13/D13 -> 1432.7778 | P13: =IFERROR(__xludf.DUMMYFUNCTION("index(sortn(GoogleFinance(B13,""high"",DATE(2020,1,1), TODAY(),""DAILY""),2,1,2,0),2,2)"),1955.0) -> 1955 | Q13: =IF(E13>O13,true,false) -> FALSE | S13: PAYTM | T13: =K13 -> 0.021219845 | V13: SANSERA | W13: =K22 -> 0.020920409 | AC13: =AC12+1 -> 12
A14: UJJIVANSFB(7) | B14: NSE:UJJIVANSFB | C14: =((manjari!C13*manjari!D13)+(HUF!B13*HUF!C13)+(vibhanshu!C13*vibhanshu!D13))/D14 -> 43.752222 | D14: =manjari!D13+vibhanshu!D13+HUF!C13 -> 36000 | E14: =IFERROR(__xludf.DUMMYFUNCTION("GOOGLEFINANCE(B14,""PRICE"")"),62.4) -> 62.4 | F14: =IFERROR(__xludf.DUMMYFUNCTION("GOOGLEFINANCE(B14,""MARKETCAP"")/10000000"),12125.5587713) -> 12125.559 | G14: =C14*D14 -> 1575080 | H14: =E14*D14 -> 2246400 | I14: 45696 | J14: =(E14-C14)/C14 -> 0.42621327 | K14: =H14/H$46 -> 0.044583108 | L14: =H14/H$46 -> 0.044583108 | M14: =IFERROR(__xludf.DUMMYFUNCTION("GOOGLEFINANCE(B14,""pe"")"),24.78) -> 24.78 | N14: =if((P14*D14-F$49)<0,0,((P14*D14)-F$49)) -> 1978000 | O14: =N14/D14 -> 54.944444 | P14: =IFERROR(__xludf.DUMMYFUNCTION("index(sortn(GoogleFinance(B14,""high"",DATE(2020,1,1), TODAY(),""DAILY""),2,1,2,0),2,2)"),68.0) -> 68 | Q14: =IF(E14>O14,true,false) -> TRUE | V14: FORCE MOTORS | W14: =#REF! -> #REF! | AB14: WINDLAS | AC14: 13 | AD14: =K6 -> 0.02590123
A15: FDC(Sajal) | B15: NSE:FDC | C15: =((manjari!C14*manjari!D14)+(HUF!B15*HUF!C15))/D15 -> 480.92838 | D15: =manjari!D14+HUF!C15 -> 3700 | E15: =IFERROR(__xludf.DUMMYFUNCTION("GOOGLEFINANCE(B15,""PRICE"")"),380.25) -> 380.25 | F15: =IFERROR(__xludf.DUMMYFUNCTION("GOOGLEFINANCE(B15,""MARKETCAP"")/10000000"),6190.85025) -> 6190.8503 | G15: =C15*D15 -> 1779435 | H15: =E15*D15 -> 1406925 | J15: =(E15-C15)/C15 -> -0.20934173 | K15: =H15/H$46 -> 0.027922494 | L15: =H15/H$46 -> 0.027922494 | M15: =IFERROR(__xludf.DUMMYFUNCTION("GOOGLEFINANCE(B15,""pe"")"),28.57) -> 28.57 | N15: =if((P15*D15-F$49)<0,0,((P15*D15)-F$49)) -> 1967745 | O15: =N15/D15 -> 531.82297 | P15: =IFERROR(__xludf.DUMMYFUNCTION("index(sortn(GoogleFinance(B15,""high"",DATE(2020,1,1), TODAY(),""DAILY""),2,1,2,0),2,2)"),658.85) -> 658.85 | Q15: =IF(E15>O15,true,false) -> FALSE | T15: =SUM(T12:T13) -> 0.021219845 | Z15: =SUM(Z11:Z12) -> #REF! | AB15: ENTERO | AC15: 14 | AD15: =K11 -> 0.036833459
A16: SILVER | B16: NSE:SILVERBEES | C16: =((HUF!B16*HUF!C16)+(manjari!D15*manjari!C15)+(vibhanshu!C14*vibhanshu!D14))/D16 -> 124 | D16: =manjari!D15+HUF!C16+vibhanshu!D14 -> 2400 | E16: =IFERROR(__xludf.DUMMYFUNCTION("GOOGLEFINANCE(B16,""PRICE"")"),240.0) -> 240 | F16: =IFERROR(__xludf.DUMMYFUNCTION("GOOGLEFINANCE(B16,""MARKETCAP"")/10000000"),"#N/A") -> #N/A | G16: =C16*D16 -> 297600 | H16: =E16*D16 -> 576000 | I16: 45901 | J16: =(E16-C16)/C16 -> 0.93548387 | K16: =H16/H$46 -> 0.011431566 | L16: =H16/H$46 -> 0.011431566 | M16: =IFERROR(__xludf.DUMMYFUNCTION("GOOGLEFINANCE(B16,""pe"")"),"#N/A") -> #N/A | N16: =if((P16*D16-F$49)<0,0,((P16*D16)-F$49)) -> 394000 | O16: =N16/D16 -> 164.16667 | P16: =IFERROR(__xludf.DUMMYFUNCTION("index(sortn(GoogleFinance(B16,""high"",DATE(2020,1,1), TODAY(),""DAILY""),2,1,2,0),2,2)"),360.0) -> 360 | Q16: =IF(E16>O16,true,false) -> TRUE | Y16: INTERNET | AC16: 15
A17: GOLD | B17: NSE:GOLDIETF | C17: =((HUF!B17*HUF!C17)+(manjari!D16*manjari!C16)+(vibhanshu!C15*vibhanshu!D15))/D17 -> 95.12 | D17: =HUF!C17+vibhanshu!D15+manjari!D16 -> 4000 | E17: =IFERROR(__xludf.DUMMYFUNCTION("GOOGLEFINANCE(B17,""PRICE"")"),128.73) -> 128.73 | F17: =IFERROR(__xludf.DUMMYFUNCTION("GOOGLEFINANCE(B17,""MARKETCAP"")/10000000"),"#N/A") -> #N/A | G17: =C17*D17 -> 380480 | H17: =E17*D17 -> 514920 | I17: 45902 | J17: =(E17-C17)/C17 -> 0.35334315 | K17: =H17/H$46 -> 0.010219344 | L17: =H17/H$46 -> 0.010219344 | M17: =IFERROR(__xludf.DUMMYFUNCTION("GOOGLEFINANCE(B17,""pe"")"),"#N/A") -> #N/A | N17: =if((P17*D17-F$49)<0,0,((P17*D17)-F$49)) -> 162000 | O17: =N17/D17 -> 40.5 | P17: =IFERROR(__xludf.DUMMYFUNCTION("index(sortn(GoogleFinance(B17,""high"",DATE(2020,1,1), TODAY(),""DAILY""),2,1,2,0),2,2)"),158.0) -> 158 | Q17: =IF(E17>O17,true,false) -> TRUE | S17: CDMO/CRAM/GENERICS | T17: 6 company basket | W17: =SUM(W12:W14) -> #REF!
A18: CSBBANK(7.6) | B18: NSE:CSBBANK | C18: =((HUF!B18*HUF!C18)+(manjari!D17*manjari!C17)+(vibhanshu!C16*vibhanshu!D16))/D18 -> 378.69052 | D18: =HUF!C18+vibhanshu!D16+manjari!D17 -> 5100 | E18: =IFERROR(__xludf.DUMMYFUNCTION("GOOGLEFINANCE(B18,""PRICE"")"),365.0) -> 365 | F18: =IFERROR(__xludf.DUMMYFUNCTION("GOOGLEFINANCE(B18,""MARKETCAP"")/10000000"),6185.92875) -> 6185.9288 | G18: =C18*D18 -> 1931321.7 | H18: =E18*D18 -> 1861500 | I18: 45952 | J18: =(E18-C18)/C18 -> -0.036152269 | K18: =H18/H$46 -> 0.036944202 | L18: =H18/H$46 -> 0.036944202 | M18: =IFERROR(__xludf.DUMMYFUNCTION("GOOGLEFINANCE(B18,""pe"")"),10.0) -> 10 | N18: =if((P18*D18-F$49)<0,0,((P18*D18)-F$49)) -> 2459440 | O18: =N18/D18 -> 482.24314 | P18: =IFERROR(__xludf.DUMMYFUNCTION("index(sortn(GoogleFinance(B18,""high"",DATE(2020,1,1), TODAY(),""DAILY""),2,1,2,0),2,2)"),574.4) -> 574.4 | Q18: =IF(E18>O18,true,false) -> FALSE | V18: BUILDING MATERIALS | Y18: % allocation | AB18: SOIC | AE18: large cap
A19: POCL(4.3) | B19: NSE:POCL | C19: =((HUF!B19*HUF!C19)+(vibhanshu!C17*vibhanshu!D17)+(manjari!C18*manjari!D18))/D19 -> 1341.3621 | D19: =HUF!C19+vibhanshu!D17+manjari!D18 -> 920 | E19: =IFERROR(__xludf.DUMMYFUNCTION("GOOGLEFINANCE(B19,""PRICE"")"),1430.5) -> 1430.5 | F19: =IFERROR(__xludf.DUMMYFUNCTION("GOOGLEFINANCE(B19,""MARKETCAP"")/10000000"),4376.539055) -> 4376.5391 | G19: =C19*D19 -> 1234053.1 | H19: =E19*D19 -> 1316060 | I19: 45964 | J19: =(E19-C19)/C19 -> 0.066453256 | K19: =H19/H$46 -> 0.026119144 | L19: =H19/H$46 -> 0.026119144 | M19: =IFERROR(__xludf.DUMMYFUNCTION("GOOGLEFINANCE(B19,""pe"")"),38.16) -> 38.16 | N19: =if((P19*D19-F$49)<0,0,((P19*D19)-F$49)) -> 981760 | O19: =N19/D19 -> 1067.1304 | P19: =IFERROR(__xludf.DUMMYFUNCTION("index(sortn(GoogleFinance(B19,""high"",DATE(2020,1,1), TODAY(),""DAILY""),2,1,2,0),2,2)"),1578.0) -> 1578 | Q19: =IF(E19>O19,true,false) -> TRUE | S19: LAURUS | T19: =K10 -> 0.079756132 | Y19: top 5 | Z19: =SUM(AD2:AD7) -> 0.40957691 | AA19: =Z19 -> 0.40957691 | AE19: mid
A20: MCX(7.5) | B20: NSE:MCX | C20: =((vibhanshu!C18*vibhanshu!D18)+(manjari!C19*manjari!D19)+(HUF!B20*HUF!C20))/D20 -> 1893.5906 | D20: =vibhanshu!D18+manjari!D19+HUF!C20 -> 1295 | E20: =IFERROR(__xludf.DUMMYFUNCTION("GOOGLEFINANCE(B20,""PRICE"")"),3098.0) -> 3098 | F20: =IFERROR(__xludf.DUMMYFUNCTION("GOOGLEFINANCE(B20,""MARKETCAP"")/10000000"),78786.6929332) -> 78786.693 | G20: =C20*D20 -> 2452199.8 | H20: =E20*D20 -> 4011910 | I20: 45972 | J20: =(E20-C20)/C20 -> 0.63604532 | K20: =H20/H$46 -> 0.079622248 | L20: =H20/H$46 -> 0.079622248 | M20: =IFERROR(__xludf.DUMMYFUNCTION("GOOGLEFINANCE(B20,""pe"")"),155.56) -> 155.56 | N20: =if((P20*D20-F$49)<0,0,((P20*D20)-F$49)) -> 3591120 | O20: =N20/D20 -> 2773.0656 | P20: =IFERROR(__xludf.DUMMYFUNCTION("index(sortn(GoogleFinance(B20,""high"",DATE(2020,1,1), TODAY(),""DAILY""),2,1,2,0),2,2)"),3136.0) -> 3136 | Q20: =IF(E20>O20,true,false) -> TRUE | S20: NEULAND | T20: =K2 -> 0.08102321 | V20: INTERARCH | W20: =K12 -> 0.027766252 | Y20: top 10 | Z20: =SUM(AD5:AD8) -> 0.28886117 | AA20: =Z19+Z20 -> 0.69843808 | AE20: small cap
A21: ACUTAS(6.6) | B21: NSE:ACUTAAS | C21: =((vibhanshu!C19*vibhanshu!D19)+(manjari!C20*manjari!D20)+(HUF!B21*HUF!C21))/D21 -> 1727 | D21: =vibhanshu!D19+manjari!D20+HUF!C21 -> 500 | E21: =IFERROR(__xludf.DUMMYFUNCTION("GOOGLEFINANCE(B21,""PRICE"")"),2745.1) -> 2745.1 | F21: =IFERROR(__xludf.DUMMYFUNCTION("GOOGLEFINANCE(B21,""MARKETCAP"")/10000000"),22474.4392056) -> 22474.439 | G21: =C21*D21 -> 863500 | H21: =E21*D21 -> 1372550 | I21: 45990 | J21: =(E21-C21)/C21 -> 0.5895194 | K21: =H21/H$46 -> 0.027240271 | L21: =H21/H$46 -> 0.027240271 | M21: =IFERROR(__xludf.DUMMYFUNCTION("GOOGLEFINANCE(B21,""pe"")"),63.29) -> 63.29 | N21: =if((P21*D21-F$49)<0,0,((P21*D21)-F$49)) -> 909500 | O21: =N21/D21 -> 1819 | P21: =IFERROR(__xludf.DUMMYFUNCTION("index(sortn(GoogleFinance(B21,""high"",DATE(2020,1,1), TODAY(),""DAILY""),2,1,2,0),2,2)"),2759.0) -> 2759 | Q21: =IF(E21>O21,true,false) -> TRUE | S21: WINDLAS | T21: =K6 -> 0.02590123 | Y21: top 15 | Z21: =SUM(AD8:AD16) -> 0.27101622 | AA21: =Z19+Z20+Z21 -> 0.9694543
A22: SANSERA(Sajal) | B22: NSE:SANSERA | C22: =((manjari!C21*manjari!D21)+(HUF!B22*HUF!C22)+(vibhanshu!C21*vibhanshu!D21))/D22 -> 1713.9131 | D22: =manjari!D21+HUF!C22+vibhanshu!D21 -> 418 | E22: =IFERROR(__xludf.DUMMYFUNCTION("GOOGLEFINANCE(B22,""PRICE"")"),2521.8) -> 2521.8 | F22: =IFERROR(__xludf.DUMMYFUNCTION("GOOGLEFINANCE(B22,""MARKETCAP"")/10000000"),15718.8966733) -> 15718.897 | G22: =C22*D22 -> 716415.68 | H22: =E22*D22 -> 1054112.4 | I22: 46011 | J22: =(E22-C22)/C22 -> 0.47136981 | K22: =H22/H$46 -> 0.020920409 | L22: =H22/H$46 -> 0.020920409 | M22: =IFERROR(__xludf.DUMMYFUNCTION("GOOGLEFINANCE(B22,""pe"")"),59.87) -> 59.87 | N22: =if((P22*D22-F$49)<0,0,((P22*D22)-F$49)) -> 647105 | O22: =N22/D22 -> 1548.0981 | P22: =IFERROR(__xludf.DUMMYFUNCTION("index(sortn(GoogleFinance(B22,""high"",DATE(2020,1,1), TODAY(),""DAILY""),2,1,2,0),2,2)"),2672.5) -> 2672.5 | Q22: =IF(E22>O22,true,false) -> TRUE | S22: SOLARA | T22: =K7 -> 0.025115607
A23: AARTIPHARM | B23: NSE:AARTIPHARM | C23: =((vibhanshu!C20*vibhanshu!D20)+(manjari!C22*manjari!D22)+(HUF!B23*HUF!C23))/D23 -> 778.92556 | D23: =vibhanshu!D20+manjari!D22+HUF!C23 -> 1350 | E23: =IFERROR(__xludf.DUMMYFUNCTION("GOOGLEFINANCE(B23,""PRICE"")"),767.0) -> 767 | F23: =IFERROR(__xludf.DUMMYFUNCTION("GOOGLEFINANCE(B23,""MARKETCAP"")/10000000"),6953.449425) -> 6953.4494 | G23: =C23*D23 -> 1051549.5 | H23: =E23*D23 -> 1035450 | I23: 46043 | J23: =(E23-C23)/C23 -> -0.015310264 | K23: =H23/H$46 -> 0.020550026 | L23: =H23/H$46 -> 0.020550026 | M23: =IFERROR(__xludf.DUMMYFUNCTION("GOOGLEFINANCE(B23,""pe"")"),32.53) -> 32.53 | N23: =if((P23*D23-F$49)<0,0,((P23*D23)-F$49)) -> 840850 | O23: =N23/D23 -> 622.85185 | P23: =IFERROR(__xludf.DUMMYFUNCTION("index(sortn(GoogleFinance(B23,""high"",DATE(2020,1,1), TODAY(),""DAILY""),2,1,2,0),2,2)"),971.0) -> 971 | Q23: =IF(E23>O23,true,false) -> TRUE | S23: AARTIPHARM | T23: =K23 -> 0.020550026
A24: SONACOMS(Sejal) | B24: NSE:SONACOMS | C24: =((vibhanshu!C22*vibhanshu!D22)+(manjari!C23*manjari!D23)+(HUF!B25*HUF!C25))/D24 -> 531.82833 | D24: =vibhanshu!D22+manjari!D23+HUF!C25 -> 1800 | E24: =IFERROR(__xludf.DUMMYFUNCTION("GOOGLEFINANCE(B24,""PRICE"")"),579.65) -> 579.65 | F24: =IFERROR(__xludf.DUMMYFUNCTION("GOOGLEFINANCE(B24,""MARKETCAP"")/10000000"),36055.8719281) -> 36055.872 | G24: =C24*D24 -> 957291 | H24: =E24*D24 -> 1043370 | I24: 46060 | J24: =(E24-C24)/C24 -> 0.089919366 | K24: =H24/H$46 -> 0.02070721 | L24: =H24/H$46 -> 0.02070721 | M24: =IFERROR(__xludf.DUMMYFUNCTION("GOOGLEFINANCE(B24,""pe"")"),56.28) -> 56.28 | N24: =if((P24*D24-F$49)<0,0,((P24*D24)-F$49)) -> 1041820 | O24: =N24/D24 -> 578.78889 | P24: =IFERROR(__xludf.DUMMYFUNCTION("index(sortn(GoogleFinance(B24,""high"",DATE(2020,1,1), TODAY(),""DAILY""),2,1,2,0),2,2)"),839.9) -> 839.9 | Q24: =IF(E24>O24,true,false) -> TRUE | S24: ACUUTAS | T24: =K21 -> 0.027240271 | V24: PEB | W24: =W21+W20 -> 0.027766252 | Y24: health care | Z24: =Z15+T25+Z26 -> #REF!
A25: SMLMAHINDRA(3.5) | B25: NSE:SMLMAH | C25: =(HUF!B24*HUF!C24)/D25 -> 4395 | D25: =HUF!C24 -> 150 | E25: =IFERROR(__xludf.DUMMYFUNCTION("GOOGLEFINANCE(B25,""PRICE"")"),3807.0) -> 3807 | F25: =IFERROR(__xludf.DUMMYFUNCTION("GOOGLEFINANCE(B25,""MARKETCAP"")/10000000"),5627.155) -> 5627.155 | G25: =C25*D25 -> 659250 | H25: =E25*D25 -> 571050 | I25: 46065 | J25: =(E25-C25)/C25 -> -0.1337884 | K25: =H25/H$46 -> 0.011333326 | L25: =H25/H$46 -> 0.011333326 | M25: =IFERROR(__xludf.DUMMYFUNCTION("GOOGLEFINANCE(B25,""pe"")"),"#N/A") -> #N/A | N25: =if((P25*D25-F$49)<0,0,((P25*D25)-F$49)) -> 332200 | O25: =N25/D25 -> 2214.6667 | P25: =IFERROR(__xludf.DUMMYFUNCTION("index(sortn(GoogleFinance(B25,""high"",DATE(2020,1,1), TODAY(),""DAILY""),2,1,2,0),2,2)"),5348.0) -> 5348 | Q25: =IF(E25>O25,true,false) -> TRUE | T25: =SUM(T18:T24) -> 0.25958648 | W25: =SUM(W20:W22) -> 0.027766252
A26: J&KBANK | B26: NSE:J&KBANK | C26: =((manjari!C24*manjari!D24)+(HUF!B26*HUF!C26)+(vibhanshu!C23*vibhanshu!D23))/D26 -> 115.70256 | D26: =vibhanshu!D23+HUF!C26+manjari!D24 -> 5877 | E26: =IFERROR(__xludf.DUMMYFUNCTION("GOOGLEFINANCE(B26,""PRICE"")"),141.1) -> 141.1 | F26: =IFERROR(__xludf.DUMMYFUNCTION("GOOGLEFINANCE(B26,""MARKETCAP"")/10000000"),15599.029994) -> 15599.03 | G26: =C26*D26 -> 679983.93 | H26: =E26*D26 -> 829244.7 | I26: 46079 | J26: =(E26-C26)/C26 -> 0.21950632 | K26: =H26/H$46 -> 0.016457579 | L26: =H26/H$46 -> 0.016457579 | M26: =IFERROR(__xludf.DUMMYFUNCTION("GOOGLEFINANCE(B26,""pe"")"),6.59) -> 6.59 | N26: =if((P26*D26-F$49)<0,0,((P26*D26)-F$49)) -> 426242.5 | O26: =N26/D26 -> 72.527225 | P26: =IFERROR(__xludf.DUMMYFUNCTION("index(sortn(GoogleFinance(B26,""high"",DATE(2020,1,1), TODAY(),""DAILY""),2,1,2,0),2,2)"),152.5) -> 152.5 | Q26: =IF(E26>O26,true,false) -> TRUE | S26: CDMO Should be 25% of portfolio | V26: OVER ALL SUM | W26: =T10+T15+T25+W6+W17+W25+Z15 -> #REF! | Y26: PHARMA | Z26: =Z33 -> 0.027922494
C31: 1288509930 | D31: 791720776
S33: its a structural story | V33: MISCELLANEOUS | W33: =Z17+Z9 -> 0 | Y33: FDC | Z33: =K15 -> 0.027922494
A34: GOLDMINERS | B34: ='US portfolio'!I54 -> 0 | C34: =B34/B39 -> 0
A35: SILVERMINERS | B35: ='US portfolio'!I55 -> 0 | C35: =B35/B39 -> 0
A36: SILVER | B36: =H16+'US portfolio'!I56 -> 663563.53 | C36: =B36/B39 -> 0.15598082
A37: GOLD | B37: =H17+'US portfolio'!I53+MANJBHAWNA!F3/2 -> 1729071.8 | C37: =B37/$B$39 -> 0.40644494
A38: GOLDFINANCIER | B38: =H18 -> 1861500 | C38: =B38/$B$39 -> 0.43757423
A39: GOLD PORTFOLIO | B39: =SUM(B34:B38) -> 4254135.3 | C39: =B39/H46 -> 0.084429565 | L39: 2780 | S39: target 25% by end of 2022 | W39: =SUM(W26:W33) -> #REF!
H40: CASH | L40: 1420
A41: PRECIOUS METALS | B41: =B37+B36+B35+B34 -> 2392635.3 | C41: =B41/H46 -> 0.047485363 | H41: ='US portfolio'!F59 -> 2008430.4 | I41: MANJ US | J41: =SUM(H41:H45) -> 4552755.9 | L41: 2500 | S41: =T25*H46 -> 13079731
H42: 9.27 | I42: HUF | J42: =J41/(J41+H48) -> 0.066522292
H43: 12.93 | I43: MANJ | S43: =T25+W6 -> 0.25958648 | T43: sajal | Y43: POWER | Z43: =Z46+Z44+Z45 -> 0.1207264
H44: 8.2 | I44: VIB | T44: khemka
H45: ='US portfolio'!F58 -> 2544295.1 | I45: VIB US | Y45: TDPOWERSYS | Z45: =K9 -> 0.1207264
H46: =SUM(H2:H26)+'US portfolio'!G51 -> 50386796 | L46: =J46/380 -> 0
F47: PORTFOLIO VALUE 13TH JUNE | G47: AIF | H47: 13500000 | L47: =J47/405 -> 0 | M47: =L47/3 -> 0 | P47: =SUM(P45:P46) -> 0
F48: 47000000 | H48: =H46+H47 -> 63886796 | I48: =J41/H48 -> 0.071262861 | L48: =J48/375 -> 0 | M48: =L48/3 -> 0
F49: =0.01*F48 -> 470000 | G49: SUM OF ALL SHEETS | H49: =vibhanshu!G27+HUF!F28+manjari!G27+'US portfolio'!G51 -> 50386796 | L49: =J49/415 -> 0
G50: HUF | H50: 32 | M50: 10.31
G51: VIBS | M51: 12.72
F52: =0.8*F49 -> 376000 | G52: MANJ | M52: 4.63
G53: 9.22 | M53: =M50+M51+M52 -> 27.66
G54: 5.16 | H54: =F48-H49 -> -3386796.4
H55: =H54/F48 -> -0.072059498
F58: 1.2
F59: 1.8
F60: 2.7 | G60: =F60/2 -> 1.35
F61: =F60+G60 -> 4.05 | G61: =F61/2 -> 2.025
F62: =F61+G61 -> 6.075 | G62: =F62/2 -> 3.0375
F63: =F62+G62 -> 9.1125 | G63: =F63/2 -> 4.55625
F64: =F63+G63 -> 13.66875
E65: Was Target Achieved
A66: 5 cr (today) | B66: 8th august | C66: 2024 | D66: returns 1.5 + 50 lakhs new money invested
A67: 7 crore | B67: 14th august | C67: 2025 | D67: 2.1+ 0.5 | E67: NO
A68: 9.6 | B68: 8th august | C68: 2026 | D68: =A68*0.3+0.5 -> 3.38
A69: =D68+A68 -> 12.98 | B69: 8th august | C69: 2027 | D69: =A69*0.3+0.6 -> 4.494
A70: =D69+A69 -> 17.474 | B70: 8th august | C70: 2028 | D70: =A70*0.3+0.7 -> 5.9422
A71: =D70+A70 -> 23.4162 | B71: 8th august | C71: 2029 | D71: =A71*0.3+0.8 -> 7.82486
A72: =D71+A71 -> 31.24106 | B72: 8th august | C72: 2030 | D72: =A72*0.3+0.9 -> 10.272318
A73: =D72+A72 -> 41.513378 | B73: 8th august | C73: 2031 | D73: =A73*0.3-0.5 -> 11.954013
A74: =D73+A73 -> 53.467391 | B74: 8th august | C74: 2032 | D74: =A74*0.3-0.5 -> 15.540217
A75: =D74+A74 -> 69.007609 | B75: 8th august | C75: 2033 | D75: =A75*0.3-0.5 -> 20.202283
A76: =D75+A75 -> 89.209891 | B76: 8th august | C76: 2034 | D76: =A76*0.3-0.5 -> 26.262967
A77: =D76+A76 -> 115.47286 | B77: 8th august | C77: 2035 | D77: =A77*0.3-0.5 -> 34.141858
A78: =D77+A77 -> 149.61472 | B78: 8th august | C78: 2036 | D78: =A78*0.3-0.5 -> 44.384415
A79: =D78+A78 -> 193.99913 | B79: 8th august | C79: 2037 | D79: =A79*0.3-0.5 -> 57.699739
A80: =D79+A79 -> 251.69887 | B80: 8th august | C80: 2038 | D80: =A80*0.3-0.5 -> 75.009661
A81: =D80+A80 -> 326.70853 | B81: 8th august | C81: 2039 | D81: =A81*0.3-0.5 -> 97.51256
A82: =D81+A81 -> 424.22109 | B82: 8th august | C82: 2040 | D82: =A82*0.3-0.5 -> 126.76633
A84: Retirement year | B84: 2030
A85: Max extended corporate life | B85: 2034
A88: Company | B88: Allocation (%) Jan sheet | C88: Company | D88: Allocation (%) December sheet | E88: Company | F88: Allocation (%) November sheet | G88: Company | H88: Allocation (%) October sheet | I88: Company | J88: Allocation (%) October sheet | K88: Company | L88: Allocation (%) September sheet | M88: Company | N88: Allocation (%) August sheet | O88: Company | P88: Allocation (%) July sheet | Q88: Company | R88: Allocation (%) June sheet | S88: Company | T88: Allocation (%) may sheet | U88: Company | V88: Allocation (%) april sheet
A89: CSB bank | B89: 7.6 | C89: CSB | E89: Samhi | F89: 6.2 | G89: csb bank | H89: 6 | I89: csb bank | J89: 6.2 | K89: Samhi Hotels | L89: 6.7 | M89: Samhi Hotels | N89: 7.5 | O89: Samhi Hotels | P89: 7.4 | Q89: Samhi Hotels | R89: 7 | S89: Samhi Hotels | T89: 7.4 | U89: Aditya Birla Capital | V89: 7.2
A90: MCX | B90: 7.5 | C90: MCX | E90: AB Capital | F90: 6 | G90: td power | H90: 6 | I90: samhi | J90: 6.2 | K90: TD Power Systems | L90: 5.2 | M90: TD Power Systems | N90: 5.5 | O90: Aditya Birla Capital | P90: 6.2 | Q90: TD Power Systems | R90: 6.1 | S90: Aditya Birla Capital | T90: 5.9 | U90: Cholamandalam Financial Holdings | V90: 6.2
A91: Ujjivan | B91: 7 | C91: Ujjivan | E91: MCX | F91: 5.9 | G91: samhi | H91: 5.8 | I91: td power | J91: 6.1 | K91: Entero Healthcare Solutions | L91: 5.1 | M91: Entero Healthcare Solutions | N91: 5.2 | O91: Force Motors | P91: 5.7 | Q91: Aditya Birla Capital | R91: 5.4 | S91: TD Power Systems | T91: 5.8 | U91: Narayana Hrudayalaya | V91: 6.1
A92: ACUUTAS | B92: 6.6 | C92: ACUUTAS | E92: Lumax | F92: 5.9 | G92: ab capital | H92: 5.6 | I92: ujjivan | J92: 5.7 | K92: Oswal Pumps | L92: 5.1 | M92: Oswal Pumps | N92: 5 | O92: TD Power Systems | P92: 5.4 | Q92: Garware Hi Tech Films | R92: 5.4 | S92: Entero Healthcare Solutions | T92: 5.8 | U92: TD Power Systems | V92: 6
A93: NH | B93: 6.1 | C93: NH | E93: NH | F93: 5.8 | G93: MCX | H93: 5.6 | I93: ab capital | J93: 4.9 | K93: paytm | L93: 5 | M93: paytm | N93: 4.7 | O93: AU Small Finance Bank | P93: 5.3 | Q93: AU Small Finance Bank | R93: 4.9 | S93: Indiamart Intermesh | T93: 5.8 | U93: Samhi Hotels | V93: 5.9
A94: SAMHI | B94: 5.8 | C94: SAMHI | E94: TD power | F94: 5.8 | G94: ujjivan | H94: 4.9 | I94: entero | J94: 4.8 | K94: Aditya Birla Capital | L94: 4.9 | M94: Aditya Birla Capital | N94: 4.7 | O94: NH | P94: 5.2 | Q94: Force Motors | R94: 4.8 | S94: AU Small Finance Bank | T94: 5.4 | U94: Cash | V94: 5.7
A95: TD Power | B95: 5.4 | C95: TD Power | E95: CSB bank | F95: 5.8 | G95: ida | H95: 4.9 | I95: goldiam | J95: 4.7 | K95: Ujjivan | L95: 5.3 | M95: Ujjivan | N95: 4.8 | O95: UJJIVAN SFB | P95: 4.9 | Q95: Entero Healthcare Solutions | R95: 4.7 | S95: Thangamayil Jewellery | T95: 5.2 | U95: One 97 Communications | V95: 5.3
A96: lumax | B96: 4.8 | C96: lumax | E96: Ujjivan | F96: 5 | G96: abdl | H96: 4.8 | I96: oswal | J96: 4.6 | K96: lumax auto technologies | L96: 4.7 | M96: nh | N96: 4.5 | O96: JM financials | P96: 4.4 | Q96: Ujjivan | R96: 4.6 | S96: Ujjivan Small Finance Bank | T96: 4.9 | U96: Thangamayil Jewellery | V96: 5.1
A97: entero | B97: 4.6 | C97: entero | E97: IDA | F97: 4.6 | G97: lumax | H97: 4.4 | I97: abdl,ida,lumax | J97: 4.3 | K97: JM financials | L97: 4.5 | M97: force motors | N97: 4.5 | O97: Lumax | P97: 4.1 | Q97: NH | R97: 4.5 | S97: Goldiam International | T97: 4.9 | U97: Garware Hi-Tech Films | V97: 4.6
A98: paytm | B98: 4.5 | C98: paytm | E98: paytm | F98: 4.4 | G98: paytm | H98: 4.2 | I98: paytm | J98: 4.2 | K98: goldiam | L98: 4.4 | M98: JM financials | N98: 4.3 | O98: pennar | P98: 4.1 | Q98: Goldiam | R98: 4.4 | S98: One 97 Communications | T98: 4.6 | U98: JM Financial | V98: 4.1
A99: physicswallah | B99: 4.5 | C99: physicswallah | E99: Acuutas | F99: 4.4 | G99: entero | H99: 4 | I99: jm , pricol | J99: 4.1 | K99: intellect,interarch,pennar,nh,abdl | L99: 4.2 | M99: lumax, pennar,abdl | N99: 4.2 | O99: Goldiam | P99: 3.8 | Q99: paytm | R99: 4.2
A100: jm | B100: 4.3 | C100: jm | E100: pricol | F100: 4.3 | G100: pocl | H100: 4 | I100: pennar | J100: 4 | M100: Thangamayil | N100: 4.2
A101: ida/interarch/pricol | B101: 3.8 | C101: ida/interarch/pricol | E101: jm | F101: 4.3 | G101: pennar,pricol,jm financials | H101: 3.8
A102: sml mahindra | B102: 3.5 | C102: sml mahindra | E102: INTERARCH/GOLDIAM/abdl | F102: 4.1
A104: Things to to
A105: 1)Finish stock scans
A106: 2)Create the prompts and keep it in sheet
A107: 3)Read q4 2025
A109: new business | C109: jcurve companies
A110: ram ratna wires
A111: precision wires
A112: bansal wires
...
